{"1":{"n":"Abasolo","l":""},"2":{"n":"Acuna","l":""},"3":{"n":"Allende","l":""},"4":{"n":"Arteaga","l":""},"5":{"n":"Candela","l":""},"6":{"n":"Castanos","l":""},"7":{"n":"Cuatro Cienegas","l":""},"8":{"n":"Escobedo","l":""},"9":{"n":"Francisco I. Madero","l":""},"10":{"n":"Frontera","l":""},"11":{"n":"General Cepeda","l":""},"12":{"n":"Guerrero","l":""},"13":{"n":"Hidalgo","l":""},"14":{"n":"Jimenez","l":""},"15":{"n":"Juarez","l":""},"16":{"n":"Lamadrid","l":""},"17":{"n":"Matamoros","l":""},"18":{"n":"Monclova","l":""},"19":{"n":"Morelos","l":""},"20":{"n":"Muzquiz","l":""},"21":{"n":"Nadadores","l":""},"22":{"n":"Nava","l":""},"23":{"n":"Ocampo","l":""},"24":{"n":"Parras","l":""},"25":{"n":"Piedras Negras","l":""},"26":{"n":"Progreso","l":""},"27":{"n":"Ramos Arizpe","l":""},"28":{"n":"Sabinas","l":""},"29":{"n":"Sacramento","l":""},"30":{"n":"Saltillo","l":""},"31":{"n":"San Buenaventura","l":""},"32":{"n":"San Juan de Sabinas","l":""},"33":{"n":"San Pedro","l":""},"34":{"n":"Sierra Mojada","l":""},"35":{"n":"Torreon","l":""},"36":{"n":"Viesca","l":""},"37":{"n":"Villa Union","l":""},"38":{"n":"Zaragoza","l":""}}