{"BA": {"n": "Buenos Aires", "l": "Buenos Aires", "s": "BA"}, "CAT": {"n": "Catamarca", "l": "Catamarca", "s": "CAT"}, "CHA": {"n": "Chaco", "l": "Chaco", "s": "CHA"}, "CHU": {"n": "Chubut", "l": "Chubut", "s": "CHU"}, "DF": {"n": "Ciudad Autónoma de Buenos Aires", "l": "Ciudad Autónoma de Buenos Aires", "s": "DF"}, "CDB": {"n": "Córdoba", "l": "Córdoba", "s": "CDB"}, "COR": {"n": "Corrientes", "l": "Corrientes", "s": "COR"}, "ERI": {"n": "Entre Ríos", "l": "Entre Ríos", "s": "ERI"}, "FOR": {"n": "Formosa", "l": "Formosa", "s": "FOR"}, "JUJ": {"n": "Jujuy", "l": "Jujuy", "s": "JUJ"}, "LPA": {"n": "La Pampa", "l": "La Pampa", "s": "LPA"}, "LRI": {"n": "La Rioja", "l": "La Rioja", "s": "LRI"}, "MEN": {"n": "Mendoza", "l": "Mendoza", "s": "MEN"}, "MIS": {"n": "Misiones", "l": "Misiones", "s": "MIS"}, "NEU": {"n": "Neuquén", "l": "Neuquén", "s": "NEU"}, "RNE": {"n": "Río Negro", "l": "Río Negro", "s": "RNE"}, "SAL": {"n": "Salta", "l": "Salta", "s": "SAL"}, "SJU": {"n": "San Juan", "l": "San Juan", "s": "SJU"}, "SLU": {"n": "San Luis", "l": "San Luis", "s": "SLU"}, "SCR": {"n": "Santa Cruz", "l": "Santa Cruz", "s": "SCR"}, "SFE": {"n": "Santa Fe", "l": "Santa Fe", "s": "SFE"}, "SDE": {"n": "Santiago del Estero", "l": "Santiago del Estero", "s": "SDE"}, "TDF": {"n": "Tierra del Fuego", "l": "Tierra del Fuego", "s": "TDF"}, "TUC": {"n": "Tucumán", "l": "Tucumán", "s": "TUC"}}
