{"BAH":{"n":"Al Bahah","l":"الباحة","s":"BAH"},"HDS":{"n":"Northern Borders","l":"الحدود الشمالية","s":"HDS"},"JWF":{"n":"Al Jawf","l":"الجوف","s":"JWF"},"MDM":{"n":"Madinah","l":"المدينة المنورة","s":"MDM"},"QSM":{"n":"Al-Qassim","l":"القصيم","s":"QSM"},"RYD":{"n":"Riyadh","l":"الرياض","s":"RYD"},"SHQ":{"n":"Eastern Province","l":"المنطقة الشرقية","s":"SHQ"},"ASI":{"n":"Asir","l":"عسير","s":"ASI"},"HAL":{"n":"Hail","l":"حائل","s":"HAL"},"JAZ":{"n":"Jazan","l":"جازان","s":"JAZ"},"MKM":{"n":"Makkah","l":"مكة المكرمة","s":"MKM"},"NJR":{"n":"Najran","l":"نجران","s":"NJR"},"TBK":{"n":"Tabuk","l":"تبوك","s":"TBK"}}