{"1":{"n":"Akumi","l":"飽海郡"},"2":{"n":"Higashimurayama","l":"東村山郡"},"3":{"n":"Higashine","l":"東根市"},"4":{"n":"Higashiokitama","l":"東置賜郡"},"5":{"n":"Higashitagawa","l":"東田川郡"},"6":{"n":"Kaminoyama","l":"上山市"},"7":{"n":"Kitamurayama","l":"北村山郡"},"8":{"n":"Mogami","l":"最上郡"},"9":{"n":"Murayama","l":"村山市"},"10":{"n":"Nagai","l":"長井市"},"11":{"n":"Nanyo","l":"南陽市"},"12":{"n":"Nishimurayama","l":"西村山郡"},"13":{"n":"Nishiokitama","l":"西置賜郡"},"14":{"n":"Obanazawa","l":"尾花沢市"},"15":{"n":"Sagae","l":"寒河江市"},"16":{"n":"Sakata","l":"酒田市"},"17":{"n":"Shinjo","l":"新庄市"},"18":{"n":"Tendo","l":"天童市"},"19":{"n":"Tsuruoka","l":"鶴岡市"},"20":{"n":"Yamagata","l":"山形市"},"21":{"n":"Yonezawa","l":"米沢市"}}