{"1":{"n":"Berakas A","l":"Berakas A"},"2":{"n":"Berakas B","l":"Berakas B"},"3":{"n":"Burong Pingai Ayer","l":"Burong Pingai Ayer"},"4":{"n":"Gadong A","l":"Gadong A"},"5":{"n":"Gadong B","l":"Gadong B"},"6":{"n":"Kianggeh","l":"Kianggeh"},"7":{"n":"Kilanas","l":"Kilanas"},"8":{"n":"Kota Batu","l":"Kota Batu"},"9":{"n":"Lumapas","l":"Lumapas"},"10":{"n":"Mentiri","l":"Mentiri"},"11":{"n":"Pengkalan Batu","l":"Pengkalan Batu"},"12":{"n":"Peramu","l":"Peramu"},"13":{"n":"Saba","l":"Saba"},"14":{"n":"Sengkurong","l":"Sengkurong"},"15":{"n":"Serasa","l":"Serasa"},"16":{"n":"Sungai Kebun","l":"Sungai Kebun"},"17":{"n":"Sungai Kedayan","l":"Sungai Kedayan"},"18":{"n":"Tamoi","l":"Tamoi"}}