{"1":{"n":"Abbadia San Salvatore","l":"Abbadia San Salvatore"},"2":{"n":"Abetone Cutigliano","l":"Abetone Cutigliano"},"3":{"n":"Agliana","l":"Agliana"},"4":{"n":"Altopascio","l":"Altopascio"},"5":{"n":"Anghiari","l":"Anghiari"},"6":{"n":"Arcidosso","l":"Arcidosso"},"7":{"n":"Arezzo","l":"Arezzo"},"8":{"n":"Asciano","l":"Asciano"},"9":{"n":"Aulla","l":"Aulla"},"10":{"n":"Badia Tedalda","l":"Badia Tedalda"},"11":{"n":"Bagni Di Lucca","l":"Bagni Di Lucca"},"12":{"n":"Bagno A Ripoli","l":"Bagno A Ripoli"},"13":{"n":"Bagnone","l":"Bagnone"},"14":{"n":"Barberino Tavarnelle","l":"Barberino Tavarnelle"},"15":{"n":"Barberino Di Mugello","l":"Barberino Di Mugello"},"16":{"n":"Barga","l":"Barga"},"17":{"n":"Bibbiena","l":"Bibbiena"},"18":{"n":"Bibbona","l":"Bibbona"},"19":{"n":"Bientina","l":"Bientina"},"20":{"n":"Borgo San Lorenzo","l":"Borgo San Lorenzo"},"21":{"n":"Borgo A Mozzano","l":"Borgo A Mozzano"},"22":{"n":"Bucine","l":"Bucine"},"23":{"n":"Buggiano","l":"Buggiano"},"24":{"n":"Buonconvento","l":"Buonconvento"},"25":{"n":"Buti","l":"Buti"},"26":{"n":"Calci","l":"Calci"},"27":{"n":"Calcinaia","l":"Calcinaia"},"28":{"n":"Calenzano","l":"Calenzano"},"29":{"n":"Camaiore","l":"Camaiore"},"30":{"n":"Campagnatico","l":"Campagnatico"},"31":{"n":"Campi Bisenzio","l":"Campi Bisenzio"},"32":{"n":"Campiglia Marittima","l":"Campiglia Marittima"},"33":{"n":"Campo nell'Elba","l":"Campo nell'Elba"},"34":{"n":"Camporgiano","l":"Camporgiano"},"35":{"n":"Cantagallo","l":"Cantagallo"},"36":{"n":"Capalbio","l":"Capalbio"},"37":{"n":"Capannoli","l":"Capannoli"},"38":{"n":"Capannori","l":"Capannori"},"39":{"n":"Capoliveri","l":"Capoliveri"},"40":{"n":"Capolona","l":"Capolona"},"41":{"n":"Capraia Isola","l":"Capraia Isola"},"42":{"n":"Capraia E Limite","l":"Capraia E Limite"},"43":{"n":"Caprese Michelangelo","l":"Caprese Michelangelo"},"44":{"n":"Careggine","l":"Careggine"},"45":{"n":"Carmignano","l":"Carmignano"},"46":{"n":"Carrara","l":"Carrara"},"47":{"n":"Casale Marittimo","l":"Casale Marittimo"},"48":{"n":"Casciana Terme Lari","l":"Casciana Terme Lari"},"49":{"n":"Cascina","l":"Cascina"},"50":{"n":"Casola In Lunigiana","l":"Casola In Lunigiana"},"51":{"n":"Casole d'Elsa","l":"Casole d'Elsa"},"52":{"n":"Castagneto Carducci","l":"Castagneto Carducci"},"53":{"n":"Castel Focognano","l":"Castel Focognano"},"54":{"n":"Castel San Niccolo","l":"Castel San Niccolò"},"55":{"n":"Castel Del Piano","l":"Castel Del Piano"},"56":{"n":"Castelfiorentino","l":"Castelfiorentino"},"57":{"n":"Castelfranco Piandisco","l":"Castelfranco Piandiscò"},"58":{"n":"Castelfranco Di Sotto","l":"Castelfranco Di Sotto"},"59":{"n":"Castell'Azzara","l":"Castell'Azzara"},"60":{"n":"Castellina Marittima","l":"Castellina Marittima"},"61":{"n":"Castellina In Chianti","l":"Castellina In Chianti"},"62":{"n":"Castelnuovo Berardenga","l":"Castelnuovo Berardenga"},"63":{"n":"Castelnuovo Di Garfagnana","l":"Castelnuovo Di Garfagnana"},"64":{"n":"Castelnuovo Di Val Di Cecina","l":"Castelnuovo Di Val Di Cecina"},"65":{"n":"Castiglion Fibocchi","l":"Castiglion Fibocchi"},"66":{"n":"Castiglion Fiorentino","l":"Castiglion Fiorentino"},"67":{"n":"Castiglione d'Orcia","l":"Castiglione d'Orcia"},"68":{"n":"Castiglione Della Pescaia","l":"Castiglione Della Pescaia"},"69":{"n":"Castiglione Di Garfagnana","l":"Castiglione Di Garfagnana"},"70":{"n":"Cavriglia","l":"Cavriglia"},"71":{"n":"Cecina","l":"Cecina"},"72":{"n":"Cerreto Guidi","l":"Cerreto Guidi"},"73":{"n":"Certaldo","l":"Certaldo"},"74":{"n":"Cetona","l":"Cetona"},"75":{"n":"Chianciano Terme","l":"Chianciano Terme"},"76":{"n":"Chianni","l":"Chianni"},"77":{"n":"Chiesina Uzzanese","l":"Chiesina Uzzanese"},"78":{"n":"Chitignano","l":"Chitignano"},"79":{"n":"Chiusdino","l":"Chiusdino"},"80":{"n":"Chiusi","l":"Chiusi"},"81":{"n":"Chiusi Della Verna","l":"Chiusi Della Verna"},"82":{"n":"Cinigiano","l":"Cinigiano"},"83":{"n":"Civitella Paganico","l":"Civitella Paganico"},"84":{"n":"Civitella In Val Di Chiana","l":"Civitella In Val Di Chiana"},"85":{"n":"Colle Di Val d'Elsa","l":"Colle Di Val d'Elsa"},"86":{"n":"Collesalvetti","l":"Collesalvetti"},"87":{"n":"Comano","l":"Comano"},"88":{"n":"Coreglia Antelminelli","l":"Coreglia Antelminelli"},"89":{"n":"Cortona","l":"Cortona"},"90":{"n":"Crespina Lorenzana","l":"Crespina Lorenzana"},"91":{"n":"Dicomano","l":"Dicomano"},"92":{"n":"Empoli","l":"Empoli"},"93":{"n":"Fabbriche Di Vergemoli","l":"Fabbriche Di Vergemoli"},"94":{"n":"Fauglia","l":"Fauglia"},"95":{"n":"Fiesole","l":"Fiesole"},"96":{"n":"Figline E Incisa Valdarno","l":"Figline E Incisa Valdarno"},"97":{"n":"Filattiera","l":"Filattiera"},"98":{"n":"Firenze","l":"Firenze"},"99":{"n":"Firenzuola","l":"Firenzuola"},"100":{"n":"Fivizzano","l":"Fivizzano"},"101":{"n":"Foiano Della Chiana","l":"Foiano Della Chiana"},"102":{"n":"Follonica","l":"Follonica"},"103":{"n":"Forte Dei Marmi","l":"Forte Dei Marmi"},"104":{"n":"Fosciandora","l":"Fosciandora"},"105":{"n":"Fosdinovo","l":"Fosdinovo"},"106":{"n":"Fucecchio","l":"Fucecchio"},"107":{"n":"Gaiole In Chianti","l":"Gaiole In Chianti"},"108":{"n":"Gallicano","l":"Gallicano"},"109":{"n":"Gambassi Terme","l":"Gambassi Terme"},"110":{"n":"Gavorrano","l":"Gavorrano"},"111":{"n":"Greve In Chianti","l":"Greve In Chianti"},"112":{"n":"Grosseto","l":"Grosseto"},"113":{"n":"Guardistallo","l":"Guardistallo"},"114":{"n":"Impruneta","l":"Impruneta"},"115":{"n":"Isola Del Giglio","l":"Isola Del Giglio"},"116":{"n":"Lajatico","l":"Lajatico"},"117":{"n":"Lamporecchio","l":"Lamporecchio"},"118":{"n":"Larciano","l":"Larciano"},"119":{"n":"Lastra A Signa","l":"Lastra A Signa"},"120":{"n":"Laterina Pergine Valdarno","l":"Laterina Pergine Valdarno"},"121":{"n":"Licciana Nardi","l":"Licciana Nardi"},"122":{"n":"Livorno","l":"Livorno"},"123":{"n":"Londa","l":"Londa"},"124":{"n":"Loro Ciuffenna","l":"Loro Ciuffenna"},"125":{"n":"Lucca","l":"Lucca"},"126":{"n":"Lucignano","l":"Lucignano"},"127":{"n":"Magliano In Toscana","l":"Magliano In Toscana"},"128":{"n":"Manciano","l":"Manciano"},"129":{"n":"Marciana","l":"Marciana"},"130":{"n":"Marciana Marina","l":"Marciana Marina"},"131":{"n":"Marciano Della Chiana","l":"Marciano Della Chiana"},"132":{"n":"Marliana","l":"Marliana"},"133":{"n":"Marradi","l":"Marradi"},"134":{"n":"Massa","l":"Massa"},"135":{"n":"Massa Marittima","l":"Massa Marittima"},"136":{"n":"Massa E Cozzile","l":"Massa E Cozzile"},"137":{"n":"Massarosa","l":"Massarosa"},"138":{"n":"Minucciano","l":"Minucciano"},"139":{"n":"Molazzana","l":"Molazzana"},"140":{"n":"Monsummano Terme","l":"Monsummano Terme"},"141":{"n":"Montaione","l":"Montaione"},"142":{"n":"Montalcino","l":"Montalcino"},"143":{"n":"Montale","l":"Montale"},"144":{"n":"Monte Argentario","l":"Monte Argentario"},"145":{"n":"Monte San Savino","l":"Monte San Savino"},"146":{"n":"Montecarlo","l":"Montecarlo"},"147":{"n":"Montecatini Val Di Cecina","l":"Montecatini Val Di Cecina"},"148":{"n":"Montecatini-Terme","l":"Montecatini-Terme"},"149":{"n":"Montelupo Fiorentino","l":"Montelupo Fiorentino"},"150":{"n":"Montemignaio","l":"Montemignaio"},"151":{"n":"Montemurlo","l":"Montemurlo"},"152":{"n":"Montepulciano","l":"Montepulciano"},"153":{"n":"Monterchi","l":"Monterchi"},"154":{"n":"Monteriggioni","l":"Monteriggioni"},"155":{"n":"Monteroni d'Arbia","l":"Monteroni d'Arbia"},"156":{"n":"Monterotondo Marittimo","l":"Monterotondo Marittimo"},"157":{"n":"Montescudaio","l":"Montescudaio"},"158":{"n":"Montespertoli","l":"Montespertoli"},"159":{"n":"Montevarchi","l":"Montevarchi"},"160":{"n":"Monteverdi Marittimo","l":"Monteverdi Marittimo"},"161":{"n":"Monticiano","l":"Monticiano"},"162":{"n":"Montieri","l":"Montieri"},"163":{"n":"Montignoso","l":"Montignoso"},"164":{"n":"Montopoli In Val d'Arno","l":"Montopoli In Val d'Arno"},"165":{"n":"Mulazzo","l":"Mulazzo"},"166":{"n":"Murlo","l":"Murlo"},"167":{"n":"Orbetello","l":"Orbetello"},"168":{"n":"Orciano Pisano","l":"Orciano Pisano"},"169":{"n":"Ortignano Raggiolo","l":"Ortignano Raggiolo"},"170":{"n":"Palaia","l":"Palaia"},"171":{"n":"Palazzuolo Sul Senio","l":"Palazzuolo Sul Senio"},"172":{"n":"Peccioli","l":"Peccioli"},"173":{"n":"Pelago","l":"Pelago"},"174":{"n":"Pescaglia","l":"Pescaglia"},"175":{"n":"Pescia","l":"Pescia"},"176":{"n":"Piancastagnaio","l":"Piancastagnaio"},"177":{"n":"Piazza Al Serchio","l":"Piazza Al Serchio"},"178":{"n":"Pienza","l":"Pienza"},"179":{"n":"Pietrasanta","l":"Pietrasanta"},"180":{"n":"Pieve Fosciana","l":"Pieve Fosciana"},"181":{"n":"Pieve Santo Stefano","l":"Pieve Santo Stefano"},"182":{"n":"Pieve A Nievole","l":"Pieve A Nievole"},"183":{"n":"Piombino","l":"Piombino"},"184":{"n":"Pisa","l":"Pisa"},"185":{"n":"Pistoia","l":"Pistoia"},"186":{"n":"Pitigliano","l":"Pitigliano"},"187":{"n":"Podenzana","l":"Podenzana"},"188":{"n":"Poggibonsi","l":"Poggibonsi"},"189":{"n":"Poggio A Caiano","l":"Poggio A Caiano"},"190":{"n":"Pomarance","l":"Pomarance"},"191":{"n":"Ponsacco","l":"Ponsacco"},"192":{"n":"Pontassieve","l":"Pontassieve"},"193":{"n":"Ponte Buggianese","l":"Ponte Buggianese"},"194":{"n":"Pontedera","l":"Pontedera"},"195":{"n":"Pontremoli","l":"Pontremoli"},"196":{"n":"Poppi","l":"Poppi"},"197":{"n":"Porcari","l":"Porcari"},"198":{"n":"Porto Azzurro","l":"Porto Azzurro"},"199":{"n":"Portoferraio","l":"Portoferraio"},"200":{"n":"Prato","l":"Prato"},"201":{"n":"Pratovecchio Stia","l":"Pratovecchio Stia"},"202":{"n":"Quarrata","l":"Quarrata"},"203":{"n":"Radda In Chianti","l":"Radda In Chianti"},"204":{"n":"Radicofani","l":"Radicofani"},"205":{"n":"Radicondoli","l":"Radicondoli"},"206":{"n":"Rapolano Terme","l":"Rapolano Terme"},"207":{"n":"Reggello","l":"Reggello"},"208":{"n":"Rignano sull'Arno","l":"Rignano sull'Arno"},"209":{"n":"Rio","l":"Rio"},"210":{"n":"Riparbella","l":"Riparbella"},"211":{"n":"Roccalbegna","l":"Roccalbegna"},"212":{"n":"Roccastrada","l":"Roccastrada"},"213":{"n":"Rosignano Marittimo","l":"Rosignano Marittimo"},"214":{"n":"Rufina","l":"Rufina"},"215":{"n":"Sambuca Pistoiese","l":"Sambuca Pistoiese"},"216":{"n":"San Casciano Dei Bagni","l":"San Casciano Dei Bagni"},"217":{"n":"San Casciano In Val Di Pesa","l":"San Casciano In Val Di Pesa"},"218":{"n":"San Gimignano","l":"San Gimignano"},"219":{"n":"San Giovanni Valdarno","l":"San Giovanni Valdarno"},"220":{"n":"San Giuliano Terme","l":"San Giuliano Terme"},"221":{"n":"San Godenzo","l":"San Godenzo"},"222":{"n":"San Marcello Piteglio","l":"San Marcello Piteglio"},"223":{"n":"San Miniato","l":"San Miniato"},"224":{"n":"San Quirico d'Orcia","l":"San Quirico d'Orcia"},"225":{"n":"San Romano In Garfagnana","l":"San Romano In Garfagnana"},"226":{"n":"San Vincenzo","l":"San Vincenzo"},"227":{"n":"Sansepolcro","l":"Sansepolcro"},"228":{"n":"Santa Croce sull'Arno","l":"Santa Croce sull'Arno"},"229":{"n":"Santa Fiora","l":"Santa Fiora"},"230":{"n":"Santa Luce","l":"Santa Luce"},"231":{"n":"Santa Maria A Monte","l":"Santa Maria A Monte"},"232":{"n":"Sarteano","l":"Sarteano"},"233":{"n":"Sassetta","l":"Sassetta"},"234":{"n":"Scandicci","l":"Scandicci"},"235":{"n":"Scansano","l":"Scansano"},"236":{"n":"Scarlino","l":"Scarlino"},"237":{"n":"Scarperia E San Piero","l":"Scarperia E San Piero"},"238":{"n":"Seggiano","l":"Seggiano"},"239":{"n":"Semproniano","l":"Semproniano"},"240":{"n":"Seravezza","l":"Seravezza"},"241":{"n":"Serravalle Pistoiese","l":"Serravalle Pistoiese"},"242":{"n":"Sestino","l":"Sestino"},"243":{"n":"Sesto Fiorentino","l":"Sesto Fiorentino"},"244":{"n":"Siena","l":"Siena"},"245":{"n":"Signa","l":"Signa"},"246":{"n":"Sillano Giuncugnano","l":"Sillano Giuncugnano"},"247":{"n":"Sinalunga","l":"Sinalunga"},"248":{"n":"Sorano","l":"Sorano"},"249":{"n":"Sovicille","l":"Sovicille"},"250":{"n":"Stazzema","l":"Stazzema"},"251":{"n":"Subbiano","l":"Subbiano"},"252":{"n":"Suvereto","l":"Suvereto"},"253":{"n":"Talla","l":"Talla"},"254":{"n":"Terranuova Bracciolini","l":"Terranuova Bracciolini"},"255":{"n":"Terricciola","l":"Terricciola"},"256":{"n":"Torrita Di Siena","l":"Torrita Di Siena"},"257":{"n":"Trequanda","l":"Trequanda"},"258":{"n":"Tresana","l":"Tresana"},"259":{"n":"Uzzano","l":"Uzzano"},"260":{"n":"Vagli Sotto","l":"Vagli Sotto"},"261":{"n":"Vaglia","l":"Vaglia"},"262":{"n":"Vaiano","l":"Vaiano"},"263":{"n":"Vecchiano","l":"Vecchiano"},"264":{"n":"Vernio","l":"Vernio"},"265":{"n":"Viareggio","l":"Viareggio"},"266":{"n":"Vicchio","l":"Vicchio"},"267":{"n":"Vicopisano","l":"Vicopisano"},"268":{"n":"Villa Basilica","l":"Villa Basilica"},"269":{"n":"Villa Collemandina","l":"Villa Collemandina"},"270":{"n":"Villafranca In Lunigiana","l":"Villafranca In Lunigiana"},"271":{"n":"Vinci","l":"Vinci"},"272":{"n":"Volterra","l":"Volterra"},"273":{"n":"Zeri","l":"Zeri"}}