{"1":{"n":"Achi","l":""},"2":{"n":"Altos del Rosario","l":""},"3":{"n":"Arenal","l":""},"4":{"n":"Arjona","l":""},"5":{"n":"Arroyohondo","l":""},"6":{"n":"Barranco de Loba","l":""},"7":{"n":"Calamar","l":""},"8":{"n":"Cantagallo","l":""},"9":{"n":"Cartagena de Indias","l":""},"10":{"n":"Cicuco","l":""},"11":{"n":"Clemencia","l":""},"12":{"n":"Cordoba","l":""},"13":{"n":"El Carmen de Bolivar","l":""},"14":{"n":"El Guamo","l":""},"15":{"n":"El Penon","l":""},"16":{"n":"Hatillo de Loba","l":""},"17":{"n":"Magangue","l":""},"18":{"n":"Mahates","l":""},"19":{"n":"Margarita","l":""},"20":{"n":"Maria La Baja","l":""},"21":{"n":"Mompos","l":""},"22":{"n":"Montecristo","l":""},"23":{"n":"Morales","l":""},"24":{"n":"Norosi","l":""},"25":{"n":"Pinillos","l":""},"26":{"n":"Regidor","l":""},"27":{"n":"Rio Viejo","l":""},"28":{"n":"San Cristobal","l":""},"29":{"n":"San Estanislao","l":""},"30":{"n":"San Fernando","l":""},"31":{"n":"San Jacinto","l":""},"32":{"n":"San Jacinto del Cauca","l":""},"33":{"n":"San Juan Nepomuceno","l":""},"34":{"n":"San Martin de Loba","l":""},"35":{"n":"San Pablo","l":""},"36":{"n":"Santa Catalina","l":""},"37":{"n":"Santa Rosa","l":""},"38":{"n":"Santa Rosa del Sur","l":""},"39":{"n":"Simiti","l":""},"40":{"n":"Soplaviento","l":""},"41":{"n":"Talaigua Nuevo","l":""},"42":{"n":"Tiquisio","l":""},"43":{"n":"Turbaco","l":""},"44":{"n":"Turbana","l":""},"45":{"n":"Villanueva","l":""},"46":{"n":"Zambrano","l":""}}