{"1":{"n":"Agua de Dios","l":""},"2":{"n":"Alban","l":""},"3":{"n":"Anapoima","l":""},"4":{"n":"Anolaima","l":""},"5":{"n":"Apulo","l":""},"6":{"n":"Arbelaez","l":""},"7":{"n":"Beltran","l":""},"8":{"n":"Bituima","l":""},"9":{"n":"Bojaca","l":""},"10":{"n":"Cabrera","l":""},"11":{"n":"Cachipay","l":""},"12":{"n":"Cajica","l":""},"13":{"n":"Caparrapi","l":""},"14":{"n":"Caqueza","l":""},"15":{"n":"Carmen de Carupa","l":""},"16":{"n":"Chaguani","l":""},"17":{"n":"Chia","l":""},"18":{"n":"Chipaque","l":""},"19":{"n":"Choachi","l":""},"20":{"n":"Choconta","l":""},"21":{"n":"Cogua","l":""},"22":{"n":"Cota","l":""},"23":{"n":"Cucunuba","l":""},"24":{"n":"El Colegio","l":""},"25":{"n":"El Penon","l":""},"26":{"n":"El Rosal","l":""},"27":{"n":"Facatativa","l":""},"28":{"n":"Fomeque","l":""},"29":{"n":"Fosca","l":""},"30":{"n":"Funza","l":""},"31":{"n":"Fuquene","l":""},"32":{"n":"Fusagasuga","l":""},"33":{"n":"Gachala","l":""},"34":{"n":"Gachancipa","l":""},"35":{"n":"Gacheta","l":""},"36":{"n":"Gama","l":""},"37":{"n":"Girardot","l":""},"38":{"n":"Granada","l":""},"39":{"n":"Guacheta","l":""},"40":{"n":"Guaduas","l":""},"41":{"n":"Guasca","l":""},"42":{"n":"Guataqui","l":""},"43":{"n":"Guatavita","l":""},"44":{"n":"Guayabal de Siquima","l":""},"45":{"n":"Guayabetal","l":""},"46":{"n":"Gutierrez","l":""},"47":{"n":"Jerusalen","l":""},"48":{"n":"Junin","l":""},"49":{"n":"La Calera","l":""},"50":{"n":"La Mesa","l":""},"51":{"n":"La Palma","l":""},"52":{"n":"La Pena","l":""},"53":{"n":"La Vega","l":""},"54":{"n":"Lenguazaque","l":""},"55":{"n":"Macheta","l":""},"56":{"n":"Madrid","l":""},"57":{"n":"Manta","l":""},"58":{"n":"Medina","l":""},"59":{"n":"Mosquera","l":""},"60":{"n":"Narino","l":""},"61":{"n":"Nemocon","l":""},"62":{"n":"Nilo","l":""},"63":{"n":"Nimaima","l":""},"64":{"n":"Nocaima","l":""},"65":{"n":"Pacho","l":""},"66":{"n":"Paime","l":""},"67":{"n":"Pandi","l":""},"68":{"n":"Paratebueno","l":""},"69":{"n":"Pasca","l":""},"70":{"n":"Puerto Salgar","l":""},"71":{"n":"Puli","l":""},"72":{"n":"Quebradanegra","l":""},"73":{"n":"Quetame","l":""},"74":{"n":"Quipile","l":""},"75":{"n":"Ricaurte","l":""},"76":{"n":"San Antonio del Tequendama","l":""},"77":{"n":"San Bernardo","l":""},"78":{"n":"San Cayetano","l":""},"79":{"n":"San Francisco","l":""},"80":{"n":"San Juan de Rioseco","l":""},"81":{"n":"Sasaima","l":""},"82":{"n":"Sesquile","l":""},"83":{"n":"Sibate","l":""},"84":{"n":"Silvania","l":""},"85":{"n":"Simijaca","l":""},"86":{"n":"Soacha","l":""},"87":{"n":"Sopo","l":""},"88":{"n":"Subachoque","l":""},"89":{"n":"Suesca","l":""},"90":{"n":"Supata","l":""},"91":{"n":"Susa","l":""},"92":{"n":"Sutatausa","l":""},"93":{"n":"Tabio","l":""},"94":{"n":"Tausa","l":""},"95":{"n":"Tena","l":""},"96":{"n":"Tenjo","l":""},"97":{"n":"Tibacuy","l":""},"98":{"n":"Tibirita","l":""},"99":{"n":"Tocaima","l":""},"100":{"n":"Tocancipa","l":""},"101":{"n":"Topaipi","l":""},"102":{"n":"Ubala","l":""},"103":{"n":"Ubaque","l":""},"104":{"n":"Une","l":""},"105":{"n":"Utica","l":""},"106":{"n":"Venecia","l":""},"107":{"n":"Vergara","l":""},"108":{"n":"Viani","l":""},"109":{"n":"Villa de San Diego de Ubate","l":""},"110":{"n":"Villagomez","l":""},"111":{"n":"Villapinzon","l":""},"112":{"n":"Villeta","l":""},"113":{"n":"Viota","l":""},"114":{"n":"Yacopi","l":""},"115":{"n":"Zipacon","l":""},"116":{"n":"Zipaquira","l":""}}