{"1":{"n":"Anantnag","l":"अनंतनाग"},"2":{"n":"Badgam","l":"बड़गाम"},"3":{"n":"Bandipore","l":"बांदीपुरा"},"4":{"n":"Baramula","l":"बारामूला"},"5":{"n":"Doda","l":"डोडा"},"6":{"n":"Ganderbal","l":"गांदरबल"},"7":{"n":"Jammu","l":"जम्मू"},"8":{"n":"Kathua","l":"कठुआ"},"9":{"n":"Kishtwar","l":"किश्तवाड़"},"10":{"n":"Kulgam","l":"कुलगाम"},"11":{"n":"Kupwara","l":"कुपवाड़ा"},"12":{"n":"Pulwama","l":"पुलवामा"},"13":{"n":"Punch","l":"पंच"},"14":{"n":"Rajouri","l":"राजौरी"},"15":{"n":"Ramban","l":"रामबन"},"16":{"n":"Reasi","l":"रियासी"},"17":{"n":"Samba","l":"सांबा"},"18":{"n":"Shupiyan","l":"शुपियां"},"19":{"n":"Srinagar","l":"श्रीनगर"},"20":{"n":"Udhampur","l":"उधमपुर"}}