{"1":{"n":"Acharipallam Vaniyakudi","l":"अचरिपल्लम् वनियकुदि"},"2":{"n":"Adirampattinam","l":"अदिरम्पत्तिनम्"},"3":{"n":"Adiyanuthu","l":"अदियनुथु"},"4":{"n":"Agaram","l":"अगरम्"},"5":{"n":"Alampalaiyam","l":"अलम्पलैयम्"},"6":{"n":"Alandur","l":"अलन्दुर्"},"7":{"n":"Alangayam","l":"अलन्गयम्"},"8":{"n":"Alangulam","l":"अलन्गुलम्"},"9":{"n":"Allapuram","l":"अल्लपुरम्"},"10":{"n":"Allinagaram","l":"अल्लिनगरम्"},"11":{"n":"Alur","l":"अलुर्"},"12":{"n":"Ambasamudram","l":"अम्बसमुद्राम"},"13":{"n":"Ambattur","l":"अम्बत्तुर्"},"14":{"n":"Ambur","l":"अम्बुर"},"15":{"n":"Ammainaickanur","l":"अम्मैनैच्कनुर्"},"16":{"n":"Anaimalai","l":"अनैमली"},"17":{"n":"Anaiyur","l":"अनैयुर्"},"18":{"n":"Anakaputhur","l":"अनकपुथुर्"},"19":{"n":"Andipalayam","l":"अन्दिपलयम्"},"20":{"n":"Andippatti","l":"अन्दिप्पत्ति"},"21":{"n":"Annamalainagar","l":"अन्नमलैनगर्"},"22":{"n":"Annur","l":"अन्नुर"},"23":{"n":"Anthiyur","l":"अन्थियुर्"},"24":{"n":"Anuppanadi","l":"अनुप्पनदि"},"25":{"n":"Arakkonam","l":"अरक्कोनम्"},"26":{"n":"Aramboli","l":"अरम्बोलि"},"27":{"n":"Arantangi","l":"अरन्तन्गि"},"28":{"n":"Arcot","l":"अर्चोत्"},"29":{"n":"Ariyalur","l":"अरियलुर्"},"30":{"n":"Arni","l":"अर्नि"},"31":{"n":"Arumanai","l":"अरुमनै"},"32":{"n":"Arumuganeri","l":"अरुमुगनेरि"},"33":{"n":"Aruppukkottai","l":"अरुप्पुक्कोत्तै"},"34":{"n":"Attimarappatti","l":"अत्तिमरप्पत्ति"},"35":{"n":"Attur","l":"अत्तुर"},"36":{"n":"Avadi","l":"अवदि"},"37":{"n":"Avalepalli","l":"अवलेपल्लि"},"38":{"n":"Avaniyapuram","l":"अवनियपुरम्"},"39":{"n":"Avinashi","l":"अविनशि"},"40":{"n":"Ayakudi","l":"अयकुदि"},"41":{"n":"Ayikudi","l":"अयिकुदि"},"42":{"n":"Ayyalur","l":"अय्यलुर्"},"43":{"n":"Ayyampettai","l":"अय्यम्पेत्तै"},"44":{"n":"Balakrishnapuram","l":"बलक्रिश्नपुरम्"},"45":{"n":"Bargur","l":"बर्गुर्"},"46":{"n":"Bhavani","l":"भवनि"},"47":{"n":"Bhikshandarkovil","l":"भिक्शन्दर्कोविल्"},"48":{"n":"Bodinayakkanur","l":"बोदिनयक्कनुर्"},"49":{"n":"Boothapandi","l":"बूथपन्दि"},"50":{"n":"Boyampalaiyam","l":"बोयम्पलैयम्"},"51":{"n":"Brahmana Periya Agraharam","l":"ब्रह्मन पेरिय अग्रहरम्"},"52":{"n":"Chengalpattu","l":"चेंगलपट्टु"},"53":{"n":"Chengam","l":"चेन्गम्"},"54":{"n":"Chennai","l":"चेन्नई"},"55":{"n":"Chennimalai","l":"चेन्निमलै"},"56":{"n":"Cheranmahadevi","l":"चेरन्महदेवि"},"57":{"n":"Chetput","l":"चेत्पुत्"},"58":{"n":"Chettinayakkanpatti","l":"चेत्तिनयक्कन्पत्ति"},"59":{"n":"Chettipalaiyam","l":"चेत्तिपलैयम्"},"60":{"n":"Cheyyar","l":"चेय्यर्"},"61":{"n":"Chidambaram","l":"चिदंबरम"},"62":{"n":"Chinna Andankovil","l":"चिन्न अन्दन्कोविल्"},"63":{"n":"Chinna Salem","l":"चिन्न सलेम्"},"64":{"n":"Chinnalapatti","l":"चिन्नलपत्ति"},"65":{"n":"Chinnamanur","l":"चिन्नमनुर्"},"66":{"n":"Chinnavadampatti","l":"चिन्नवदम्पत्ति"},"67":{"n":"Chokkanathapuram","l":"चोक्कनथपुरम्"},"68":{"n":"Coimbatore","l":"keayampattuർ"},"69":{"n":"Colachel","l":"चोलचेल्"},"70":{"n":"Coonoor","l":"कुन्नूर"},"71":{"n":"Cuddalore","l":"कडलूर"},"72":{"n":"Cumbum","l":"चुम्बुम्"},"73":{"n":"Darasuram","l":"दरसुरम्"},"74":{"n":"Denkanikota","l":"देन्कनिकोत"},"75":{"n":"Devadanapatti","l":"देवदानपट्टी"},"76":{"n":"Devakottai","l":"देवकोट्टई"},"77":{"n":"Devarshola","l":"देवर्शोल"},"78":{"n":"Dharapuram","l":"धारापुरम"},"79":{"n":"Dharmapuram","l":"धर्मपुरम्"},"80":{"n":"Dharmapuri","l":"धर्मपुरी"},"81":{"n":"Dindigul","l":"दिंडुक्कल"},"82":{"n":"Edaicode","l":"एदैचोदे"},"83":{"n":"Elandakuttai","l":"एलन्दकुत्तै"},"84":{"n":"Ellakkudi","l":"एल्लक्कुदि"},"85":{"n":"Elumalai","l":"एलुमलइ"},"86":{"n":"Erode","l":"इरोड"},"87":{"n":"Eruvadi","l":"एरुवदि"},"88":{"n":"Ezhudesam","l":"एऴुदेसम्"},"89":{"n":"Gingee","l":"गिन्जी"},"90":{"n":"Gobichettipalayam","l":"गोबिचेट्टिपलयम"},"91":{"n":"Gudalur","l":"गुदलुर्"},"92":{"n":"Gudiyatham","l":"गुदियथम्"},"93":{"n":"Guduvancheri","l":"गुदुवन्चेरि"},"94":{"n":"Gummidipundi","l":"गुम्मिदिपुन्दि"},"95":{"n":"Harur","l":"हरुर्"},"96":{"n":"Hosur","l":"होसुर्"},"97":{"n":"Idaiyarpalaiyam","l":"इदैयर्पलैयम्"},"98":{"n":"Idangansalai","l":"इदन्गन्सलै"},"99":{"n":"Idappadi","l":"इदप्पदि"},"100":{"n":"Ilaiyankudi","l":"इलैयन्कुदि"},"101":{"n":"Inam Maniyachi","l":"इनम् मनियचि"},"102":{"n":"Injambakkam","l":"इन्जम्बक्कम"},"103":{"n":"Irugur","l":"इरुगुर्"},"104":{"n":"Jalakandapuram","l":"जलकण्डापुरम"},"105":{"n":"Jalarpet","l":"जलर्पेत्"},"106":{"n":"Jalladiampet","l":"जल्लदिअम्पेत्"},"107":{"n":"Jambai","l":"जम्बै"},"108":{"n":"Jayamkondacholapuram","l":"जयम्कोन्दचोलपुरम्"},"109":{"n":"Jujuvadi","l":"जुजुवदि"},"110":{"n":"Kadayal","l":"कदयल्"},"111":{"n":"Kadayanallur","l":"कदयनल्लुर्"},"112":{"n":"Kadiganpalli","l":"कदिगन्पल्लि"},"113":{"n":"Kaikalapettai","l":"कैकलपेत्तै"},"114":{"n":"Kalakkadu","l":"कलक्कदु"},"115":{"n":"Kalappatti","l":"कलप्पत्ति"},"116":{"n":"Kalinjur","l":"कलिन्जुर्"},"117":{"n":"Kallakkurichchi","l":"कल्लक्कुरिच्चि"},"118":{"n":"Kallakurichi","l":"कल्लकुरिचि"},"119":{"n":"Kallamchavadi","l":"कल्लम्चवदि"},"120":{"n":"Kallidaikurichi","l":"कल्लिदैकुरिचि"},"121":{"n":"Kallukuttam","l":"कल्लुकुत्तम्"},"122":{"n":"Kalugumalai","l":"कलुगुमलै"},"123":{"n":"Kamayakkavundanpatti","l":"कमयक्कवुन्दन्पत्ति"},"124":{"n":"Kammivapettai","l":"कम्मिवपेत्तै"},"125":{"n":"Kanchipuram","l":"कांचिपुरम"},"126":{"n":"Kangayam","l":"कन्गयम्"},"127":{"n":"Kangeyanallur","l":"कन्गेयनल्लुर्"},"128":{"n":"Kannampalaiyam","l":"कन्नम्पलैयम्"},"129":{"n":"Kannanendal","l":"कन्ननेन्दल्"},"130":{"n":"Kannankurichchi","l":"कन्नन्कुरिच्चि"},"131":{"n":"Kanniyakumari","l":"कन्नियकुमरि"},"132":{"n":"Kappiyara","l":"कप्पियर"},"133":{"n":"Karaikkudi","l":"करैक्कुदि"},"134":{"n":"Karaippudur","l":"करैप्पुदुर्"},"135":{"n":"Karamadai","l":"காரமடை"},"136":{"n":"Kariapatti","l":"करिअपत्ति"},"137":{"n":"Karingal","l":"करिन्गल्"},"138":{"n":"Karumandi Chellipalaiyam","l":"करुमन्दि चेल्लिपलैयम्"},"139":{"n":"Karumattampatti","l":"करुमत्तम्पत्ति"},"140":{"n":"Karur","l":"करुर"},"141":{"n":"Kasipalaiyam","l":"कसिपलैयम्"},"142":{"n":"Katpadi","l":"कत्पदि"},"143":{"n":"Kattatturai","l":"कत्तत्तुरै"},"144":{"n":"Kattivakkam","l":"कत्तिवक्कम्"},"145":{"n":"Kattumannarkoil","l":"कत्तुमन्नरकोइल"},"146":{"n":"Kavanur","l":"कवनुर्"},"147":{"n":"Kaveripatnam","l":"कवेरिपत्नम्"},"148":{"n":"Kayalpattinam","l":"कयल्पट्टिनम"},"149":{"n":"Keezhkulam","l":"कीऴ्कुलम्"},"150":{"n":"Kerkandi","l":"केर्कन्दि"},"151":{"n":"Kil Bhuvanagiri","l":"किल् भुवनगिरि"},"152":{"n":"Kilakarai","l":"कीलाकाराई"},"153":{"n":"Kilapavoor","l":"किलपवूर्"},"154":{"n":"Kodaikanal","l":"कोदैकनल्"},"155":{"n":"Kollancode","l":"कोल्लन्चोदे"},"156":{"n":"Kollivayal","l":"कोल्लिवयल्"},"157":{"n":"Kombai","l":"कोम्बै"},"158":{"n":"Kondalampatti","l":"कोन्दलम्पत्ति"},"159":{"n":"Kondasamudram","l":"कोन्दसमुद्रम्"},"160":{"n":"Koothanallur","l":"कूतानल्लूर"},"161":{"n":"Koothappar","l":"कूथप्पर्"},"162":{"n":"Kotagiri","l":"कोटागिरी"},"163":{"n":"Kothanallur","l":"कोथनल्लुर्"},"164":{"n":"Kotivakkam","l":"कोतिवक्कम्"},"165":{"n":"Kottaikadu","l":"कोत्तैकदु"},"166":{"n":"Kottaikuppam","l":"कोत्तैकुप्पम्"},"167":{"n":"Kottur","l":"कोत्तुर्"},"168":{"n":"Kovilpatti","l":"कोभिलपट्टी"},"169":{"n":"Krishnagiri","l":"कृष्णगिरि"},"170":{"n":"Kulasegaram","l":"कुलसेगरम्"},"171":{"n":"Kulattuppalaiyam","l":"कुलत्तुप्पलैयम्"},"172":{"n":"Kulittalai","l":"कुलित्तलै"},"173":{"n":"Kullattur","l":"कुल्लत्तुर्"},"174":{"n":"Kumarapalaiyam","l":"कुमरपलैयम्"},"175":{"n":"Kumarapalayam","l":"कुमरपलयम्"},"176":{"n":"Kumbakonam","l":"कुंभकोणम"},"177":{"n":"Kuniyamuttur","l":"कुनियमुत्तुर्"},"178":{"n":"Kurichchi","l":"कुरिच्चि"},"179":{"n":"Kurinjippadi","l":"कुरिन्जिप्पदि"},"180":{"n":"Kuthalam","l":"कुथलम्"},"181":{"n":"Kuzhithurai","l":"कुऴिथुरै"},"182":{"n":"Lakkanahalli","l":"लक्कनहल्लि"},"183":{"n":"Lalgudi","l":"लालगुडी"},"184":{"n":"Lalpettai","l":"लल्पेत्तै"},"185":{"n":"Madambakkam","l":"मदम्बक्कम्"},"186":{"n":"Madattukkulam","l":"मदत्तुक्कुलम्"},"187":{"n":"Madhavaram","l":"मदावरम"},"188":{"n":"Madipakkam","l":"मदिप्पक्कम"},"189":{"n":"Madukkarai","l":"मदुकरै"},"190":{"n":"Madukkur","l":"मदुक्कुर्"},"191":{"n":"Madurai","l":"मदुरई"},"192":{"n":"Maduraivayal","l":"मदुरैवयल्"},"193":{"n":"Madurantakam","l":"मदुरन्तकम्"},"194":{"n":"Maduravoyal","l":"मदुरभोयल"},"195":{"n":"Mahabalipuram","l":"மாமல்லபுரம்"},"196":{"n":"Mallasamudram","l":"मल्लसमुद्रम्"},"197":{"n":"Mamsapuram","l":"मम्सपुरम्"},"198":{"n":"Manali","l":"மணலி"},"199":{"n":"Manamadurai","l":"मनमदुराय"},"200":{"n":"Manapparai","l":"मनप्परै"},"201":{"n":"Mandapam","l":"मन्दपम्"},"202":{"n":"Mangalam","l":"मन्गलम्"},"203":{"n":"Mannachanallur","l":"मन्नचनल्लुर्"},"204":{"n":"Mannarai","l":"मन्नरै"},"205":{"n":"Mannargudi","l":"मन्नर्गुडी"},"206":{"n":"Mappilaiurani","l":"मप्पिलैउरनि"},"207":{"n":"Maraimalainagar","l":"मरैमलैनगर्"},"208":{"n":"Marakkanam","l":"मरक्कनम्"},"209":{"n":"Marthandam","l":"मर्थन्दम्"},"210":{"n":"Mathur","l":"मथुर्"},"211":{"n":"Mattigiri","l":"मत्तिगिरि"},"212":{"n":"Mayiladuthurai","l":"मयिलदुथुराय"},"213":{"n":"Mechcheri","l":"मेच्चेरि"},"214":{"n":"Meddappakkam","l":"मेद्दप्पक्कम्"},"215":{"n":"Meenambakkam","l":"मीनम्बक्कम्"},"216":{"n":"Melmadai","l":"मेल्मदै"},"217":{"n":"Melur","l":"मेलुर्"},"218":{"n":"Methukummal","l":"मेथुकुम्मल्"},"219":{"n":"Mettupalayam","l":"मेट्टुपालयम"},"220":{"n":"Mettur","l":"मेत्तुर्"},"221":{"n":"Milavittan","l":"मिलवित्तन्"},"222":{"n":"Minjur","l":"मिन्जुर्"},"223":{"n":"Mugalivakkam","l":"মুঘলীবক্কম"},"224":{"n":"Mukondapalli","l":"मुकोन्दपल्लि"},"225":{"n":"Mulakumud","l":"मुलकुमुद्"},"226":{"n":"Mulanur","l":"मुलनुर्"},"227":{"n":"Murugampalaiyam","l":"मुरुगम्पलैयम्"},"228":{"n":"Musiri","l":"मुसिरि"},"229":{"n":"Muthupet","l":"मुथुपेत्"},"230":{"n":"Muttanampalaiyam","l":"मुत्तनम्पलैयम्"},"231":{"n":"Muttayyapuram","l":"मुत्तय्यपुरम्"},"232":{"n":"Nagapattinam","l":"நாகப்பட்டினம்"},"233":{"n":"Nagercoil","l":"நாகர்கோவில்"},"234":{"n":"Nalambur","l":"नलम्बुर्"},"235":{"n":"Nallavila","l":"नल्लविल"},"236":{"n":"Nalloor","l":"नल्लूर्"},"237":{"n":"Nallur","l":"नल्लुर्"},"238":{"n":"Namagiripettai","l":"नमगिरिपेत्तै"},"239":{"n":"Namakkal","l":"नमक्कल्"},"240":{"n":"Nambiyur","l":"नम्बियुर्"},"241":{"n":"Nangavaram","l":"नन्गवरम्"},"242":{"n":"Nanjikkottai","l":"नन्जिक्कोत्तै"},"243":{"n":"Naranammalpuram","l":"नरनम्मल्पुरम्"},"244":{"n":"Narasimhanaickenpalayam","l":"नरसिम्हनैच्केन्पलयम्"},"245":{"n":"Narasingapuram","l":"नरसिन्गपुरम्"},"246":{"n":"Naravarikuppam","l":"नरवरिकुप्पम्"},"247":{"n":"Natham","l":"नथम्"},"248":{"n":"Nattappettai","l":"नत्तप्पेत्तै"},"249":{"n":"Navalpattu","l":"नवल्पत्तु"},"250":{"n":"Nayanakulam","l":"नयनकुलम्"},"251":{"n":"Nazareth","l":"नज़रेथ्"},"252":{"n":"Neelagiri","l":"नीलगिरि"},"253":{"n":"Neelankarai","l":"नीलंकरई"},"254":{"n":"Nellikkuppam","l":"नेल्लिक्कुप्पम्"},"255":{"n":"Nerkunram","l":"नेर्कुन्रम्"},"256":{"n":"Nerupperichchal","l":"नेरुप्पेरिच्चल्"},"257":{"n":"Neyveli","l":"নেয়বেলি"},"258":{"n":"Nilakottai","l":"निलकोत्तै"},"259":{"n":"Oddanchathiram","l":"ओद्दन्चथिरम्"},"260":{"n":"Omalur","l":"ओमलुर्"},"261":{"n":"Ooty","l":"उदगमंदलम"},"262":{"n":"Ottakkadai","l":"ओत्तक्कदै"},"263":{"n":"Pachchal","l":"पच्चल्"},"264":{"n":"Pacode","l":"पचोदे"},"265":{"n":"Padiyanallur","l":"पदियनल्लुर्"},"266":{"n":"Padmanabhapuram","l":"பத்மனாபபுரம்"},"267":{"n":"Painkulam","l":"पैन्कुलम्"},"268":{"n":"Palaiyam","l":"पलैयम्"},"269":{"n":"Palaiyampatti","l":"पलैयम्पत्ति"},"270":{"n":"Palakkodu","l":"पलक्कोदु"},"271":{"n":"Palangarai","l":"पलन्गरै"},"272":{"n":"Palani","l":"पलनी"},"273":{"n":"Palappallam","l":"पलप्पल्लम्"},"274":{"n":"Palavakkam","l":"पलवक्कम्"},"275":{"n":"Palavansathu","l":"पलवन्सथु"},"276":{"n":"Palladam","l":"पल्लदम्"},"277":{"n":"Pallappatti","l":"पल्लप्पत्ति"},"278":{"n":"Pallavaram","l":"पल्लवरम्"},"279":{"n":"Pallikaranai","l":"পল্লিকারানাই"},"280":{"n":"Pallikonda","l":"पल्लिकोन्द"},"281":{"n":"Pallipalayam","l":"पल्लिपलयम्"},"282":{"n":"Pallippatti","l":"पल्लिप्पत्ति"},"283":{"n":"Palugal","l":"पलुगल्"},"284":{"n":"Pammal","l":"पम्मल्"},"285":{"n":"Panakkudi","l":"पनक्कुदि"},"286":{"n":"Panruti","l":"পানরুটি"},"287":{"n":"Papanasam","l":"பாபநாசம்"},"288":{"n":"Pappakurichchi","l":"पप्पकुरिच्चि"},"289":{"n":"Paramagudi","l":"परमगुदि"},"290":{"n":"Paramathi Velur","l":"परमथि वेलुर्"},"291":{"n":"Parangipettai","l":"परन्गिपेत्तै"},"292":{"n":"Parassala","l":"परस्सल"},"293":{"n":"Paravai","l":"परवै"},"294":{"n":"Pattamadai","l":"पत्तमदै"},"295":{"n":"Pattukkottai","l":"पट्टुक्कोटै"},"296":{"n":"Peddanayakkanpalaiyam","l":"पेद्दनयक्कन्पलैयम्"},"297":{"n":"Pennadam","l":"पेन्नदम्"},"298":{"n":"Pennagaram","l":"पेन्नगरम्"},"299":{"n":"Perambalur","l":"पेरम्बलूरु"},"300":{"n":"Peranampattu","l":"पेरनम्पत्तु"},"301":{"n":"Peravurani","l":"पेरवुरनि"},"302":{"n":"Periya Semur","l":"पेरिय सेमुर्"},"303":{"n":"Periyakottai","l":"पेरियकोत्तै"},"304":{"n":"Periyakulam","l":"पेरियकुलम्"},"305":{"n":"Periyanayakkanpalaiyam","l":"பெரியநாயக்கன்பாளையம்"},"306":{"n":"Periyapatti","l":"पेरियपत्ति"},"307":{"n":"Perundurai","l":"पेरुन्दुरै"},"308":{"n":"Perungudi","l":"पेरुन्गुदि"},"309":{"n":"Perunkalattu","l":"पेरुन्कलत्तु"},"310":{"n":"Podaturpet","l":"பொதட்டூர்பேட்டை"},"311":{"n":"Polichalur","l":"पोलिचलुर्"},"312":{"n":"Pollachi","l":"पोल्लाची"},"313":{"n":"Polur","l":"पोलुर्"},"314":{"n":"Ponmana","l":"पोन्मन"},"315":{"n":"Ponneri","l":"পোন্নেরি"},"316":{"n":"Poonamalle","l":"पूनमल्ले"},"317":{"n":"Porur","l":"পোরুর"},"318":{"n":"Pottaneri Nallakavundanpatti","l":"पोत्तनेरि नल्लकवुन्दन्पत्ति"},"319":{"n":"Pottanur","l":"पोत्तनुर्"},"320":{"n":"Pudukkottai","l":"পুড়ুক্কোত্তাই"},"321":{"n":"Pudupattanam","l":"पुदुपत्तनम्"},"322":{"n":"Pudur","l":"पुदुर्"},"323":{"n":"Pugalur","l":"पुगलुर्"},"324":{"n":"Puliyankannu","l":"पुलियन्कन्नु"},"325":{"n":"Puliyankudi","l":"पुलियन्कुदि"},"326":{"n":"Punjai Puliyampatti","l":"पुन्जै पुलियम्पत्ति"},"327":{"n":"Puzhal","l":"पुऴल्"},"328":{"n":"Rajakilpakkam","l":"रजकिल्पक्कम्"},"329":{"n":"Rajapalayam","l":"रजपलयम्"},"330":{"n":"Rakkiyapalaiyam","l":"रक्कियपलैयम्"},"331":{"n":"Ramachettipalaiyam","l":"रमचेत्तिपलैयम्"},"332":{"n":"Ramanathapuram","l":"रामनाथपुरम"},"333":{"n":"Ramapuram","l":"रमपुरम्"},"334":{"n":"Rameswaram","l":"रामेश्वरम"},"335":{"n":"Ranipet","l":"रनिपेत्"},"336":{"n":"Rasipuram","l":"रसिपुरम्"},"337":{"n":"Reddipalaiyam","l":"रेद्दिपलैयम्"},"338":{"n":"Reethapuram","l":"रीथपुरम्"},"339":{"n":"Saint Thomas Mount","l":"सैन्त् थोमस् मोउन्त्"},"340":{"n":"Salamedu","l":"सलमेदु"},"341":{"n":"Salangaippalaiyam","l":"सलन्गैप्पलैयम्"},"342":{"n":"Salem","l":"सेलम"},"343":{"n":"Samalapuram","l":"समलपुरम्"},"344":{"n":"Samburvadakara","l":"सम्बुर्वदकर"},"345":{"n":"Sankagiri","l":"सन्कगिरि"},"346":{"n":"Sankarankovil","l":"सन्करन्कोविल्"},"347":{"n":"Sankarapatti","l":"सन्करपत्ति"},"348":{"n":"Sankaraperi","l":"सन्करपेरि"},"349":{"n":"Sathyamangalam","l":"सत्यमंगलम"},"350":{"n":"Sattur","l":"सत्तुर्"},"351":{"n":"Senapparetti","l":"सेनप्परेत्ति"},"352":{"n":"Sendamangalam","l":"सेन्दमन्गलम्"},"353":{"n":"Settiyarpatti","l":"सेत्तियर्पत्ति"},"354":{"n":"Settur","l":"सेत्तुर्"},"355":{"n":"Sevilimedu","l":"सेविलिमेदु"},"356":{"n":"Shenkottai","l":"செங்கோட்டை"},"357":{"n":"Sholavandan","l":"শোলাবন্দন"},"358":{"n":"Sholinganallur","l":"शोलिन्गनल्लुर्"},"359":{"n":"Sholinghur","l":"शोलिन्घुर्"},"360":{"n":"Silappadi","l":"सिलप्पदि"},"361":{"n":"Singampunari","l":"सिंगमपुनरी"},"362":{"n":"Singanallur","l":"सिन्गनल्लुर्"},"363":{"n":"Sirkazhi","l":"सिर्कऴि"},"364":{"n":"Sirumugai","l":"சிறுமுகை"},"365":{"n":"Sithurajapuram","l":"सिथुरजपुरम्"},"366":{"n":"Sivaganga","l":"शिवगङ्गा"},"367":{"n":"Sivagiri","l":"सिवगिरि"},"368":{"n":"Sivagirippatti","l":"सिवगिरिप्पत्ति"},"369":{"n":"Sivakasi","l":"चिवकाचि"},"370":{"n":"Sriperumbudur","l":"स्रिपेरुम्बुदुर्"},"371":{"n":"Srivaikuntam","l":"स्रिवैकुन्तम्"},"372":{"n":"Srivilliputhur","l":"श्रीविल्लीपुतूर"},"373":{"n":"Srvanampatti","l":"स्र्वनम्पत्ति"},"374":{"n":"Suleswaranpatti","l":"सुलेस्वरन्पत्ति"},"375":{"n":"Sulur","l":"सुलूर"},"376":{"n":"Sundakkampalaiyam","l":"सुन्दक्कम्पलैयम्"},"377":{"n":"Surampatti","l":"सुरम्पत्ति"},"378":{"n":"Surandai","l":"सुरन्दै"},"379":{"n":"Suryampalaiyam","l":"सुर्यम्पलैयम्"},"380":{"n":"Tadikombu","l":"तदिकोम्बु"},"381":{"n":"Tambaram","l":"तांबरम"},"382":{"n":"Tammampatti","l":"तम्मम्पत्ति"},"383":{"n":"Tandoni","l":"तन्दोनि"},"384":{"n":"Taramangalam","l":"तरमन्गलम्"},"385":{"n":"Tattankuttai","l":"तत्तन्कुत्तै"},"386":{"n":"Teni","l":"तेनि"},"387":{"n":"Tevaram","l":"तेवरम्"},"388":{"n":"Thanjavur","l":"tancavuർ"},"389":{"n":"Tharangambadi","l":"থারাঙ্গামবাড়ি"},"390":{"n":"Thenkasi","l":"थेन्कसि"},"391":{"n":"Thimiri","l":"थिमिरि"},"392":{"n":"Thiruthani","l":"थिरुथनि"},"393":{"n":"Thiruthuraipoondi","l":"थिरुथुरैपून्दि"},"394":{"n":"Thiruvaiyaru","l":"थिरुवैयरु"},"395":{"n":"Thiruvarur","l":"तिरुवरुर"},"396":{"n":"Thoothukudi","l":"तूतुकुडि"},"397":{"n":"Thorapadi","l":"थोरपदि"},"398":{"n":"Thuraiyur","l":"थुरैयुर्"},"399":{"n":"Tindal","l":"तिन्दल्"},"400":{"n":"Tindivanam","l":"திண்டிவனம்"},"401":{"n":"Tinnanur","l":"तिन्ननुर्"},"402":{"n":"Tiruchchendur","l":"तिरुच्चेन्दुर्"},"403":{"n":"Tiruchengode","l":"तिरुचेंगोड"},"404":{"n":"Tiruchirappalli","l":"ट्रिचिमलैदुर्गम्"},"405":{"n":"Tirukkalikkunram","l":"तिरुक्कलिक्कुन्रम्"},"406":{"n":"Tirukkoyilur","l":"तिरुक्कोयिलुर्"},"407":{"n":"Tirumangalam","l":"तिरुमन्गलम्"},"408":{"n":"Tirumeshi","l":"तिरुमेशि"},"409":{"n":"Tirumuruganpundi","l":"तिरुमुरुगन्पुन्दि"},"410":{"n":"Tirunageswaram","l":"तिरुनगेस्वरम्"},"411":{"n":"Tirunelveli","l":"तिरुनलवेली"},"412":{"n":"Tirupattur","l":"तिरुपत्तुर्"},"413":{"n":"Tiruppalai","l":"तिरुप्पलै"},"414":{"n":"Tirupparangunram","l":"तिरुप्परन्गुन्रम्"},"415":{"n":"Tiruppur","l":"तिरुपुर"},"416":{"n":"Tiruppuvanam","l":"तिरुप्पुवनम्"},"417":{"n":"Tiruttangal","l":"तिरुत्तन्गल्"},"418":{"n":"Tiruvallur","l":"तिरुवल्लुर"},"419":{"n":"Tiruvankod","l":"तिरुवन्कोद्"},"420":{"n":"Tiruvannamalai","l":"திருவண்ணாமலை"},"421":{"n":"Tiruvattar","l":"तिरुवत्तर्"},"422":{"n":"Tiruverumbur","l":"तिरुवेरुम्बुर्"},"423":{"n":"Tiruvottiyur","l":"तिरुवोत्तियुर्"},"424":{"n":"Tisaiyanvilai","l":"तिसैयन्विलै"},"425":{"n":"Tittagudi","l":"तित्तगुदि"},"426":{"n":"Tondalam","l":"तोन्दलम्"},"427":{"n":"Tondi","l":"तोन्दि"},"428":{"n":"Triparappu","l":"त्रिपरप्पु"},"429":{"n":"Tudiyalur","l":"तुदियलुर्"},"430":{"n":"Turaiyur","l":"तुरैयुर्"},"431":{"n":"Tuvagudi","l":"तुवगुदि"},"432":{"n":"Tyagadurgam","l":"त्यगदुर्गम्"},"433":{"n":"Udangudi","l":"उदन्गुदि"},"434":{"n":"Udumalaippettai","l":"उदुमलैप्पेत्तै"},"435":{"n":"Ullagaram","l":"उल्लगरम्"},"436":{"n":"Ulundurpet","l":"उलुन्दुर्पेत्"},"437":{"n":"Unamaucheri","l":"उनमौचेरि"},"438":{"n":"Unnamalaikadai","l":"उन्नमलैकदै"},"439":{"n":"Usilampatti","l":"उसिलम्पत्ति"},"440":{"n":"Uttamapalaiyam","l":"उत्तमपलैयम्"},"441":{"n":"Uttangarai","l":"उत्तन्गरै"},"442":{"n":"Uttiramerur","l":"उत्तिरमेरुर्"},"443":{"n":"Uttukuli","l":"उत्तुकुलि"},"444":{"n":"V.S.K.Valasai (Dindigul-Dist.)","l":"व् स् क् वलसै (दिन्दिगुल् दिस्त् )"},"445":{"n":"Vadakarai Kil Pidagai","l":"वदकरै किल् पिदगै"},"446":{"n":"Vadakkanandal","l":"वदक्कनन्दल्"},"447":{"n":"Vadakku Valliyur","l":"वदक्कु वल्लियुर्"},"448":{"n":"Vadakku Viravanallur","l":"वदक्कु विरवनल्लुर्"},"449":{"n":"Vadamadurai","l":"वडमदुरा"},"450":{"n":"Vadavalli","l":"वदवल्लि"},"451":{"n":"Vadipatti","l":"वाडिपट्टी"},"452":{"n":"Valasaravakkam","l":"वलसरवक्कम्"},"453":{"n":"Valavanur","l":"वलवनूर"},"454":{"n":"Vallam","l":"वल्लम्"},"455":{"n":"Valparai","l":"वल्परै"},"456":{"n":"Valvachatottam","l":"वल्वचतोत्तम्"},"457":{"n":"Vandalur","l":"वन्दलुर्"},"458":{"n":"Vandavasi","l":"वन्दवसि"},"459":{"n":"Vandiyur","l":"वन्दियुर्"},"460":{"n":"Vaniyambadi","l":"वनियामबादी"},"461":{"n":"Vasudevanallur","l":"वसुदेवनल्लुर्"},"462":{"n":"Vathirairuppu","l":"वथिरैरुप्पु"},"463":{"n":"Vattalkundu","l":"वत्तल्कुन्दु"},"464":{"n":"Vazhapadi","l":"वऴपदि"},"465":{"n":"Vedaraniyam","l":"वेदरनियम्"},"466":{"n":"Velampalaiyam","l":"वेलम्पलैयम्"},"467":{"n":"Vellakkinar","l":"वेल्लक्किनर्"},"468":{"n":"Vellakkovil","l":"वेल्लक्कोविल्"},"469":{"n":"Vellalur","l":"वेल्ललुर्"},"470":{"n":"Vellore","l":"भेल्लोर"},"471":{"n":"Velur","l":"वेलुर्"},"472":{"n":"Vengattur","l":"वेन्गत्तुर्"},"473":{"n":"Vengikkal","l":"वेन्गिक्कल्"},"474":{"n":"Verukulambu","l":"वेरुकुलम्बु"},"475":{"n":"Vettaikkaranpudur","l":"वेत्तैक्करन्पुदुर्"},"476":{"n":"Vettavalam","l":"वेत्तवलम्"},"477":{"n":"Vikramasingapuram","l":"विक्रमसिन्गपुरम्"},"478":{"n":"Vilangudi","l":"विलन्गुदि"},"479":{"n":"Vilankurichi","l":"विलन्कुरिचि"},"480":{"n":"Vilattikulam","l":"विलत्तिकुलम्"},"481":{"n":"Villukuri","l":"विल्लुकुरि"},"482":{"n":"Villupuram","l":"விழுப்புரம்"},"483":{"n":"Virakeralam","l":"विरकेरलम्"},"484":{"n":"Virapandi","l":"विरपन्दि"},"485":{"n":"Virappanchathiram","l":"विरप्पन्चथिरम्"},"486":{"n":"Viraraghavapuram","l":"विररघवपुरम्"},"487":{"n":"Virnur","l":"विर्नुर्"},"488":{"n":"Virudhachalam","l":"विरुद्धचलम्"},"489":{"n":"Virudunagar","l":"विरुदुनगर्"},"490":{"n":"Virugambakkam","l":"विरुगम्बक्कम्"},"491":{"n":"Visharam","l":"विशरम्"},"492":{"n":"Viswanatham","l":"विस्वनथम्"},"493":{"n":"Vriddhachalam","l":"व्रिद्धचलम्"},"494":{"n":"Walajapet","l":"वलजपेत्"},"495":{"n":"Wellington","l":"वेल्लिन्ग्तोन्"}}
