{"1":{"n":"Abdelkader Azil","l":"المتكوك"},"2":{"n":"Ain Djasser","l":"عين جاسر"},"3":{"n":"Ain Touta","l":"عين التوتة"},"4":{"n":"Ain Yagout","l":"عين ياقوت"},"5":{"n":"Arris","l":"أريس"},"6":{"n":"Barika","l":"بريكة"},"7":{"n":"Batna","l":"باتنة"},"8":{"n":"Ben Foudala El Hakania","l":"بنى فضالة الحقانية"},"9":{"n":"Bitam","l":"بيطام"},"10":{"n":"Boulhilat","l":"بوالحيلات"},"11":{"n":"Boumaguer","l":"بومقر"},"12":{"n":"Boumia","l":"بومية"},"13":{"n":"Bouzina","l":"بوزينة"},"14":{"n":"Chemora","l":"شمرة"},"15":{"n":"Chir","l":"شير"},"16":{"n":"Djerma","l":"جرمة"},"17":{"n":"Djezar","l":"الجزار"},"18":{"n":"El Hassi","l":"الحاسى"},"19":{"n":"El Madher","l":"المعذر"},"20":{"n":"Fesdis","l":"فسديس"},"21":{"n":"Foum Toub","l":"فم الطوب"},"22":{"n":"Ghassira","l":"غسيرة"},"23":{"n":"Gosbat","l":"القصبات"},"24":{"n":"Guigba","l":"قيقبة"},"25":{"n":"Hidoussa","l":"حيدوسة"},"26":{"n":"Ichmoul","l":"إيشمول"},"27":{"n":"Inoughissen","l":"اينوغيسن"},"28":{"n":"Kimmel","l":"كيمل"},"29":{"n":"Ksar Bellezma","l":"قصر بلازمة"},"30":{"n":"Lazrou","l":"لازرو"},"31":{"n":"Lemsane","l":"لمسان"},"32":{"n":"Maafa","l":"معافة"},"33":{"n":"Mdoukel","l":"أمدوكل"},"34":{"n":"Menaa","l":"منعة"},"35":{"n":"Merouana","l":"مروانة"},"36":{"n":"NGaous","l":"نقاوس"},"37":{"n":"Oued Chaaba","l":"وادى الشعبة"},"38":{"n":"Oued El Ma","l":"وادى الماء"},"39":{"n":"Oued Taga","l":"وادى الطا قة"},"40":{"n":"Ouled Ammar","l":"أولاد عمار"},"41":{"n":"Ouled Aouf","l":"أولاد عوف"},"42":{"n":"Ouled Fadel","l":"أولاد فاضل"},"43":{"n":"Ouled Sellam","l":"أولاد سلام"},"44":{"n":"Ouled Si Slimane","l":"أولاد سى سليمان"},"45":{"n":"Ouyoun El Assafir","l":"عيون العصا فير"},"46":{"n":"Rahbat","l":"الرحبات"},"47":{"n":"Ras El Aioun","l":"رأس العيون"},"48":{"n":"Sefiane","l":"سفيان"},"49":{"n":"Seggana","l":"سقانة"},"50":{"n":"Seriana","l":"سريانة"},"51":{"n":"Talkhamt","l":"تالخمت"},"52":{"n":"Taxlent","l":"تاكسلانت"},"53":{"n":"Tazoult","l":"تازولت"},"54":{"n":"Teniet El Abed","l":"ثنية العابد"},"55":{"n":"Tighanimine","l":"تغانمين"},"56":{"n":"Tigherghar","l":"تغرغار"},"57":{"n":"Tilatou","l":"تيلاطو"},"58":{"n":"Timgad","l":"تيمقاد"},"59":{"n":"TKout","l":"تكوت"},"60":{"n":"Zanet El Beida","l":"زانة البيضاء"}}