{
  "1": {
    "n": "La Rioja",
    "l": "La Rioja"
  },
  "2": {
    "n": "Chilecito",
    "l": "Chilecito"
  },
  "3": {
    "n": "Aimogasta",
    "l": "Aimogasta"
  },
  "4": {
    "n": "Chamical",
    "l": "Chamical"
  },
  "5": {
    "n": "Chepes",
    "l": "Chepes"
  },
  "6": {
    "n": "Villa Unión",
    "l": "Villa Unión"
  },
  "7": {
    "n": "Anillaco",
    "l": "Anillaco"
  },
  "8": {
    "n": "Olta",
    "l": "Olta"
  },
  "9": {
    "n": "Famatina",
    "l": "Famatina"
  },
  "10": {
    "n": "Ulapes",
    "l": "Ulapes"
  }
}
