{"1":{"n":"Aleksandrovskij Rajon","l":"Александровский район"},"2":{"n":"Gorochoveckij Rajon","l":"Гороховецкий район"},"3":{"n":"Gus-Chrustalnyj","l":"Городской округ город Гусь-Хрустальный"},"4":{"n":"Gus-Chrustalnyj Rajon","l":"Гусь-Хрустальный район"},"5":{"n":"Jurjev-Polskij Rajon","l":"Юрьев-Польский район"},"6":{"n":"Kameskovskij Rajon","l":"Камешковский район"},"7":{"n":"Kirzacskij Rajon","l":"Киржачский район"},"8":{"n":"Kolcuginskij Rajon","l":"Кольчугинский район"},"9":{"n":"Kovrov","l":"Ковров"},"10":{"n":"Kovrovskij Rajon","l":"Ковровский район"},"11":{"n":"Melenkovskij Rajon","l":"Меленковский район"},"12":{"n":"Murom","l":"Городской округ Муром"},"13":{"n":"Muromskij Rajon","l":"Муромский район"},"14":{"n":"Petusinskij Rajon","l":"Петушинский район"},"15":{"n":"Raduznyj","l":"Радужный"},"16":{"n":"Selivanovskij Rajon","l":"Селивановский район"},"17":{"n":"Sobinskij Rajon","l":"Собинский район"},"18":{"n":"Sudogodskij Rajon","l":"Судогодский район"},"19":{"n":"Suzdalskij Rajon","l":"Суздальский район"},"20":{"n":"Vjaznikovskij Rajon","l":"Вязниковский район"},"21":{"n":"Vladimir","l":"Городской округ город Владимир"}}