{"1":{"n":"Abu Musa","l":"ابوموسی"},"2":{"n":"Bandar Abbas","l":"بندرعباس"},"3":{"n":"Bandar Charak","l":"بندرچارک"},"4":{"n":"Bandar e Khamir","l":"بندرخمیر"},"5":{"n":"Bandar-e Lengeh","l":"بندرلنگه"},"6":{"n":"Bandar-e-Jask","l":"بندرجاسک"},"7":{"n":"Bastak","l":"بستک"},"8":{"n":"Bikah","l":"بیکا"},"9":{"n":"Dargahan","l":"درگهان"},"10":{"n":"Dehbarez","l":"دهبارز"},"11":{"n":"Fareghan","l":"فارغان"},"12":{"n":"Fin","l":"فین"},"13":{"n":"Gowharan","l":"گوهران"},"14":{"n":"Hajiabad","l":"حاجی آباد"},"15":{"n":"Hashtbandi","l":"هشتبندی"},"16":{"n":"Hormuz","l":"هرمز"},"17":{"n":"Jenah","l":"جناح"},"18":{"n":"Kang","l":"کنگ"},"19":{"n":"Kish","l":"کیش"},"20":{"n":"Kushk-e Nar","l":"کوشکنار"},"21":{"n":"Minab","l":"میناب"},"22":{"n":"Parsian","l":"پارسیان"},"23":{"n":"Qaleh Qazi","l":"قلعه قاضی"},"24":{"n":"Qeshm","l":"قشم"},"25":{"n":"Ruydar","l":"رویدر"},"26":{"n":"Sardasht","l":"سردشت"},"27":{"n":"Seerik","l":"سیریک"},"28":{"n":"Senderk","l":"سندرک"},"29":{"n":"Suza","l":"سوزا"},"30":{"n":"Takht","l":"تخت"},"31":{"n":"Ziaratali","l":"زیارتعلی"}}
