{"1":{"n":"Astara","l":"سطر"},"2":{"n":"Banavara","l":"بانوره"},"3":{"n":"Bynagan","l":"باینگان"},"4":{"n":"Bysatavan","l":"بیستون"},"5":{"n":"Eslamabad-e Gharb","l":"اسلام آبادغرب"},"6":{"n":"Gavadyn","l":"گودین"},"7":{"n":"Ghavara","l":"گهواره"},"8":{"n":"Gilan-e Gharb","l":"گیلانغرب"},"9":{"n":"Halashy","l":"هلشی"},"10":{"n":"Hamyl","l":"حمیل"},"11":{"n":"Harsin","l":"هرسین"},"12":{"n":"Javanrud","l":"جوانرود"},"13":{"n":"Kangavar","l":"کنگاور"},"14":{"n":"Karanad","l":"کرند"},"15":{"n":"Kavazaran","l":"کوزران"},"16":{"n":"Kermanshah","l":"کرمانشاه"},"17":{"n":"Myn Rahan","l":"میان راهان"},"18":{"n":"Navadasha","l":"نودشه"},"19":{"n":"Navasavad","l":"نوسود"},"20":{"n":"Paveh","l":"پاوه"},"21":{"n":"Qasr-e Shirin","l":"قصرشیرین"},"22":{"n":"Rabat","l":"رباط"},"23":{"n":"Ravansar","l":"روانسر"},"24":{"n":"Ryjab","l":"ریجاب"},"25":{"n":"Sahneh","l":"صحنه"},"26":{"n":"Saramasat","l":"سرمست"},"27":{"n":"Sarpol-e Dhahab","l":"سرپل ذهاب"},"28":{"n":"Savamar","l":"سومار"},"29":{"n":"Shahav","l":"شاهو"},"30":{"n":"Sonqor","l":"سنقر"},"31":{"n":"Tazeh Abad","l":"تازه آباد"},"32":{"n":"Zagala","l":"ازگله"}}