{"1":{"n":"Sanandaj","l":"سنندج"},"2":{"n":"Saqqez","l":"سقز"},"3":{"n":"Marivan","l":"مریوان"},"4":{"n":"Baneh","l":"بانه"},"5":{"n":"Qorveh","l":"قروه"},"6":{"n":"Kamyaran","l":"کامیاران"},"7":{"n":"Bijar","l":"بیجار"},"8":{"n":"Divandarreh","l":"دیواندره"},"9":{"n":"Dehgolan","l":"دهگلان"},"10":{"n":"Kani Dinar","l":"کانیدینار"},"11":{"n":"Serishabad","l":"سریشآباد"},"12":{"n":"Delbaran","l":"دلبران"},"13":{"n":"Sarvabad","l":"سروآباد"},"14":{"n":"Yasukand","l":"یاسوکند"},"15":{"n":"Muchesh","l":"موچش"},"16":{"n":"Oraman Takht","l":"اورامان تخت"},"17":{"n":"Saheb","l":"صاحب"},"18":{"n":"Armardeh","l":"آرمرده"},"19":{"n":"Babashani","l":"بابارشانی"},"20":{"n":"Top Aghaj","l":"توپآغاج"},"21":{"n":"Zarrineh","l":"زرینه"},"22":{"n":"Kani Sur","l":"کانیسور"},"23":{"n":"Buin-e Sofla","l":"بوئینسفلی"},"24":{"n":"Shuyesha","l":"شویشه"},"25":{"n":"Dezaj","l":"دزج"},"26":{"n":"Bolbanabad","l":"بلبانآباد"},"27":{"n":"Pir Taj","l":"پیرتاج"},"28":{"n":"Chenareh","l":"چناره"},"29":{"n":"Barda Rasheh","l":"بردهرشه"},"30":{"n":"Shuy","l":"شوی"},"31":{"n":"Hezar Kani","l":"هزارکانیان"},"32":{"n":"Khalifeh Tarkhan","l":"خلیفه ترخان"}}