{"1":{"n":"Powiat bedzinski","l":""},"2":{"n":"Powiat bielski","l":""},"3":{"n":"Powiat Bielsko-Biała","l":""},"4":{"n":"Powiat bierunsko-ledzinski","l":""},"5":{"n":"Powiat Bytom","l":""},"6":{"n":"Powiat Chorzow","l":""},"7":{"n":"Powiat cieszynski","l":""},"8":{"n":"Powiat Czestochowa","l":""},"9":{"n":"Powiat czestochowski","l":""},"10":{"n":"Powiat Dabrowa Gornicza","l":""},"11":{"n":"Powiat Gliwice","l":""},"12":{"n":"Powiat gliwicki","l":""},"13":{"n":"Powiat Jastrzebie-Zdroj","l":""},"14":{"n":"Powiat Jaworzno","l":""},"15":{"n":"Powiat Katowice","l":""},"16":{"n":"Powiat kłobucki","l":""},"17":{"n":"Powiat lubliniecki","l":""},"18":{"n":"Powiat mikołowski","l":""},"19":{"n":"Powiat Mysłowice","l":""},"20":{"n":"Powiat myszkowski","l":""},"21":{"n":"Powiat Piekary Slaskie","l":""},"22":{"n":"Powiat pszczynski","l":""},"23":{"n":"Powiat raciborski","l":""},"24":{"n":"Powiat Ruda Slaska","l":""},"25":{"n":"Powiat rybnicki","l":""},"26":{"n":"Powiat Rybnik","l":""},"27":{"n":"Powiat Siemianowice Slaskie","l":""},"28":{"n":"Powiat Sosnowiec","l":""},"29":{"n":"Powiat Swietochłowice","l":""},"30":{"n":"Powiat tarnogorski","l":""},"31":{"n":"Powiat Tychy","l":""},"32":{"n":"Powiat wodzisławski","l":""},"33":{"n":"Powiat Zabrze","l":""},"34":{"n":"Powiat zawiercianski","l":""},"35":{"n":"Powiat Zory","l":""},"36":{"n":"Powiat zywiecki","l":""}}