{"1":{"n":"Anadia","l":"Anadia"},"2":{"n":"Arapiraca","l":"Arapiraca"},"3":{"n":"Atalaia","l":"Atalaia"},"4":{"n":"Barra De Santo Antonio","l":"Barra De Santo Antônio"},"5":{"n":"Barra De Sao Miguel","l":"Barra De São Miguel"},"6":{"n":"Batalha","l":"Batalha"},"7":{"n":"Belo Monte","l":"Belo Monte"},"8":{"n":"Belem","l":"Belém"},"9":{"n":"Boca Da Mata","l":"Boca Da Mata"},"10":{"n":"Branquinha","l":"Branquinha"},"11":{"n":"Cacimbinhas","l":"Cacimbinhas"},"12":{"n":"Cajueiro","l":"Cajueiro"},"13":{"n":"Campestre","l":"Campestre"},"14":{"n":"Campo Alegre","l":"Campo Alegre"},"15":{"n":"Campo Grande","l":"Campo Grande"},"16":{"n":"Canapi","l":"Canapi"},"17":{"n":"Capela","l":"Capela"},"18":{"n":"Carneiros","l":"Carneiros"},"19":{"n":"Cha Preta","l":"Chã Preta"},"20":{"n":"Coite Do Noia","l":"Coité Do Nóia"},"21":{"n":"Colonia Leopoldina","l":"Colônia Leopoldina"},"22":{"n":"Coqueiro Seco","l":"Coqueiro Seco"},"23":{"n":"Coruripe","l":"Coruripe"},"24":{"n":"Craibas","l":"Craíbas"},"25":{"n":"Delmiro Gouveia","l":"Delmiro Gouveia"},"26":{"n":"Dois Riachos","l":"Dois Riachos"},"27":{"n":"Estrela De Alagoas","l":"Estrela De Alagoas"},"28":{"n":"Feira Grande","l":"Feira Grande"},"29":{"n":"Feliz Deserto","l":"Feliz Deserto"},"30":{"n":"Flexeiras","l":"Flexeiras"},"31":{"n":"Girau Do Ponciano","l":"Girau Do Ponciano"},"32":{"n":"Ibateguara","l":"Ibateguara"},"33":{"n":"Igaci","l":"Igaci"},"34":{"n":"Igreja Nova","l":"Igreja Nova"},"35":{"n":"Inhapi","l":"Inhapi"},"36":{"n":"Jacare Dos Homens","l":"Jacaré Dos Homens"},"37":{"n":"Jacuipe","l":"Jacuípe"},"38":{"n":"Japaratinga","l":"Japaratinga"},"39":{"n":"Jaramataia","l":"Jaramataia"},"40":{"n":"Jequia Da Praia","l":"Jequiá Da Praia"},"41":{"n":"Joaquim Gomes","l":"Joaquim Gomes"},"42":{"n":"Jundia","l":"Jundiá"},"43":{"n":"Junqueiro","l":"Junqueiro"},"44":{"n":"Lagoa Da Canoa","l":"Lagoa Da Canoa"},"45":{"n":"Limoeiro De Anadia","l":"Limoeiro De Anadia"},"46":{"n":"Maceio","l":"Maceió"},"47":{"n":"Major Isidoro","l":"Major Isidoro"},"48":{"n":"Mar Vermelho","l":"Mar Vermelho"},"49":{"n":"Maragogi","l":"Maragogi"},"50":{"n":"Maravilha","l":"Maravilha"},"51":{"n":"Marechal Deodoro","l":"Marechal Deodoro"},"52":{"n":"Maribondo","l":"Maribondo"},"53":{"n":"Mata Grande","l":"Mata Grande"},"54":{"n":"Matriz De Camaragibe","l":"Matriz De Camaragibe"},"55":{"n":"Messias","l":"Messias"},"56":{"n":"Minador Do Negrao","l":"Minador Do Negrão"},"57":{"n":"Monteiropolis","l":"Monteirópolis"},"58":{"n":"Murici","l":"Murici"},"59":{"n":"Novo Lino","l":"Novo Lino"},"60":{"n":"Olho d`Agua Grande","l":"Olho d`Água Grande"},"61":{"n":"Olho d`Agua Das Flores","l":"Olho d`Água Das Flores"},"62":{"n":"Olho d`Agua Do Casado","l":"Olho d`Água Do Casado"},"63":{"n":"Olivenca","l":"Olivença"},"64":{"n":"Ouro Branco","l":"Ouro Branco"},"65":{"n":"Palestina","l":"Palestina"},"66":{"n":"Palmeira Dos Indios","l":"Palmeira Dos Índios"},"67":{"n":"Pariconha","l":"Pariconha"},"68":{"n":"Paripueira","l":"Paripueira"},"69":{"n":"Passo De Camaragibe","l":"Passo De Camaragibe"},"70":{"n":"Paulo Jacinto","l":"Paulo Jacinto"},"71":{"n":"Penedo","l":"Penedo"},"72":{"n":"Piacabucu","l":"Piaçabuçu"},"73":{"n":"Pilar","l":"Pilar"},"74":{"n":"Pindoba","l":"Pindoba"},"75":{"n":"Piranhas","l":"Piranhas"},"76":{"n":"Porto Calvo","l":"Porto Calvo"},"77":{"n":"Porto Real Do Colegio","l":"Porto Real Do Colégio"},"78":{"n":"Porto De Pedras","l":"Porto De Pedras"},"79":{"n":"Poco Das Trincheiras","l":"Poço Das Trincheiras"},"80":{"n":"Pao De Acucar","l":"Pão De Açúcar"},"81":{"n":"Quebrangulo","l":"Quebrangulo"},"82":{"n":"Rio Largo","l":"Rio Largo"},"83":{"n":"Roteiro","l":"Roteiro"},"84":{"n":"Santa Luzia Do Norte","l":"Santa Luzia Do Norte"},"85":{"n":"Santana Do Ipanema","l":"Santana Do Ipanema"},"86":{"n":"Santana Do Mundau","l":"Santana Do Mundaú"},"87":{"n":"Satuba","l":"Satuba"},"88":{"n":"Senador Rui Palmeira","l":"Senador Rui Palmeira"},"89":{"n":"Sao Bras","l":"São Brás"},"90":{"n":"Sao Jose Da Laje","l":"São José Da Laje"},"91":{"n":"Sao Jose Da Tapera","l":"São José Da Tapera"},"92":{"n":"Sao Luis Do Quitunde","l":"São Luís Do Quitunde"},"93":{"n":"Sao Miguel Dos Campos","l":"São Miguel Dos Campos"},"94":{"n":"Sao Miguel Dos Milagres","l":"São Miguel Dos Milagres"},"95":{"n":"Sao Sebastiao","l":"São Sebastião"},"96":{"n":"Tanque d`Arca","l":"Tanque d`Arca"},"97":{"n":"Taquarana","l":"Taquarana"},"98":{"n":"Teotonio Vilela","l":"Teotônio Vilela"},"99":{"n":"Traipu","l":"Traipu"},"100":{"n":"Uniao Dos Palmares","l":"União Dos Palmares"},"101":{"n":"Vicosa","l":"Viçosa"},"102":{"n":"Agua Branca","l":"Água Branca"}}