{"1":{"n":"Aqjaıyq aydany","l":"Ақжайық ауданы"},"2":{"n":"Bokeıordasy aydany","l":"Бөкейордасы ауданы"},"3":{"n":"Borli aydany","l":"Бөрлі ауданы"},"4":{"n":"Janaqala aydany","l":"Жаңақала ауданы"},"5":{"n":"Janibek aydany","l":"Жәнібек ауданы"},"6":{"n":"Kaztalovka aydany","l":"Казталовка ауданы"},"7":{"n":"Oral","l":"Орал Қ.Ә."},"8":{"n":"Qaratobe aydany","l":"Қаратөбе ауданы"},"9":{"n":"Shyngyrlay aydany","l":"Шыңғырлау ауданы"},"10":{"n":"Syrym aydany","l":"Сырым ауданы"},"11":{"n":"Tasqala aydany","l":"Тасқала ауданы"},"12":{"n":"Terekti aydany","l":"Теректі ауданы"},"13":{"n":"Zelenov aydany","l":"Зеленов ауданы"}}