{"1":{"n":"Ughelli North","l":""},"2":{"n":"Warri South","l":""},"3":{"n":"Isoko South","l":""},"4":{"n":"Ughelli South","l":""},"5":{"n":"Burutu","l":""},"6":{"n":"Ethiope West","l":""},"7":{"n":"Ethiope East","l":""},"8":{"n":"Uvwie","l":""},"9":{"n":"Ika North East","l":""},"10":{"n":"Sapele","l":""},"11":{"n":"Ika South","l":""},"12":{"n":"Oshimili South","l":""},"13":{"n":"Ndokwa West","l":""},"14":{"n":"Isoko North","l":""},"15":{"n":"Udu","l":""},"16":{"n":"Aniocha South","l":""},"17":{"n":"Warri North","l":""},"18":{"n":"Okpe","l":""},"19":{"n":"Ukwuani","l":""},"20":{"n":"Oshimili North","l":""},"21":{"n":"Warri South West","l":""},"22":{"n":"Aniocha North","l":""},"23":{"n":"Ndokwa East","l":""},"24":{"n":"Bomadi","l":""},"25":{"n":"Patani","l":""}}