{"1":{"n":"Abbyville","l":""},"2":{"n":"Abilene","l":""},"3":{"n":"Admire","l":""},"4":{"n":"Agenda","l":""},"5":{"n":"Agra","l":""},"6":{"n":"Albert","l":""},"7":{"n":"Alden","l":""},"8":{"n":"Alexander","l":""},"9":{"n":"Allen","l":""},"10":{"n":"Alma","l":""},"11":{"n":"Almena","l":""},"12":{"n":"Alta Vista","l":""},"13":{"n":"Altamont","l":""},"14":{"n":"Alton","l":""},"15":{"n":"Altoona","l":""},"16":{"n":"Americus","l":""},"17":{"n":"Andale","l":""},"18":{"n":"Andover","l":""},"19":{"n":"Anthony","l":""},"20":{"n":"Arcadia","l":""},"21":{"n":"Argonia","l":""},"22":{"n":"Arkansas City","l":""},"23":{"n":"Arlington","l":""},"24":{"n":"Arma","l":""},"25":{"n":"Arnold","l":""},"26":{"n":"Ashland","l":""},"27":{"n":"Assaria","l":""},"28":{"n":"Atchison","l":""},"29":{"n":"Athol","l":""},"30":{"n":"Atlanta","l":""},"31":{"n":"Attica","l":""},"32":{"n":"Atwood","l":""},"33":{"n":"Auburn","l":""},"34":{"n":"Augusta","l":""},"35":{"n":"Aurora","l":""},"36":{"n":"Axtell","l":""},"37":{"n":"Baileyville","l":""},"38":{"n":"Baldwin City","l":""},"39":{"n":"Barnard","l":""},"40":{"n":"Barnes","l":""},"41":{"n":"Bartlett","l":""},"42":{"n":"Basehor","l":""},"43":{"n":"Baxter Springs","l":""},"44":{"n":"Bazine","l":""},"45":{"n":"Beattie","l":""},"46":{"n":"Beaumont","l":""},"47":{"n":"Beeler","l":""},"48":{"n":"Belle Plaine","l":""},"49":{"n":"Belleville","l":""},"50":{"n":"Beloit","l":""},"51":{"n":"Belpre","l":""},"52":{"n":"Belvue","l":""},"53":{"n":"Bendena","l":""},"54":{"n":"Benedict","l":""},"55":{"n":"Bennington","l":""},"56":{"n":"Bentley","l":""},"57":{"n":"Benton","l":""},"58":{"n":"Bern","l":""},"59":{"n":"Berryton","l":""},"60":{"n":"Beverly","l":""},"61":{"n":"Bird City","l":""},"62":{"n":"Bison","l":""},"63":{"n":"Blue Mound","l":""},"64":{"n":"Blue Rapids","l":""},"65":{"n":"Bluff City","l":""},"66":{"n":"Bogue","l":""},"67":{"n":"Bonner Springs","l":""},"68":{"n":"Bremen","l":""},"69":{"n":"Brewster","l":""},"70":{"n":"Bronson","l":""},"71":{"n":"Brookville","l":""},"72":{"n":"Brownell","l":""},"73":{"n":"Bucklin","l":""},"74":{"n":"Bucyrus","l":""},"75":{"n":"Buffalo","l":""},"76":{"n":"Buhler","l":""},"77":{"n":"Bunker Hill","l":""},"78":{"n":"Burden","l":""},"79":{"n":"Burdett","l":""},"80":{"n":"Burdick","l":""},"81":{"n":"Burlingame","l":""},"82":{"n":"Burlington","l":""},"83":{"n":"Burns","l":""},"84":{"n":"Burr Oak","l":""},"85":{"n":"Burrton","l":""},"86":{"n":"Bushton","l":""},"87":{"n":"Byers","l":""},"88":{"n":"Caldwell","l":""},"89":{"n":"Cambridge","l":""},"90":{"n":"Caney","l":""},"91":{"n":"Canton","l":""},"92":{"n":"Carbondale","l":""},"93":{"n":"Cassoday","l":""},"94":{"n":"Catharine","l":""},"95":{"n":"Cawker City","l":""},"96":{"n":"Cedar","l":""},"97":{"n":"Cedar Point","l":""},"98":{"n":"Cedar Vale","l":""},"99":{"n":"Centerville","l":""},"100":{"n":"Centralia","l":""},"101":{"n":"Chanute","l":""},"102":{"n":"Chapman","l":""},"103":{"n":"Chase","l":""},"104":{"n":"Chautauqua","l":""},"105":{"n":"Cheney","l":""},"106":{"n":"Cherokee","l":""},"107":{"n":"Cherryvale","l":""},"108":{"n":"Chetopa","l":""},"109":{"n":"Cimarron","l":""},"110":{"n":"Circleville","l":""},"111":{"n":"Claflin","l":""},"112":{"n":"Clay Center","l":""},"113":{"n":"Clayton","l":""},"114":{"n":"Clearview City","l":""},"115":{"n":"Clearwater","l":""},"116":{"n":"Clifton","l":""},"117":{"n":"Clyde","l":""},"118":{"n":"Coats","l":""},"119":{"n":"Coffeyville","l":""},"120":{"n":"Colby","l":""},"121":{"n":"Coldwater","l":""},"122":{"n":"Collyer","l":""},"123":{"n":"Colony","l":""},"124":{"n":"Columbus","l":""},"125":{"n":"Colwich","l":""},"126":{"n":"Concordia","l":""},"127":{"n":"Conway Springs","l":""},"128":{"n":"Coolidge","l":""},"129":{"n":"Copeland","l":""},"130":{"n":"Corning","l":""},"131":{"n":"Cottonwood Falls","l":""},"132":{"n":"Council Grove","l":""},"133":{"n":"Courtland","l":""},"134":{"n":"Crestline","l":""},"135":{"n":"Cuba","l":""},"136":{"n":"Cummings","l":""},"137":{"n":"Cunningham","l":""},"138":{"n":"Damar","l":""},"139":{"n":"Danville","l":""},"140":{"n":"De Soto","l":""},"141":{"n":"Dearing","l":""},"142":{"n":"Deerfield","l":""},"143":{"n":"Delia","l":""},"144":{"n":"Delphos","l":""},"145":{"n":"Denison","l":""},"146":{"n":"Dennis","l":""},"147":{"n":"Denton","l":""},"148":{"n":"Derby","l":""},"149":{"n":"Dexter","l":""},"150":{"n":"Dighton","l":""},"151":{"n":"Dodge City","l":""},"152":{"n":"Dorrance","l":""},"153":{"n":"Douglass","l":""},"154":{"n":"Dover","l":""},"155":{"n":"Downs","l":""},"156":{"n":"Dresden","l":""},"157":{"n":"Durham","l":""},"158":{"n":"Dwight","l":""},"159":{"n":"Easton","l":""},"160":{"n":"Edgerton","l":""},"161":{"n":"Edna","l":""},"162":{"n":"Edson","l":""},"163":{"n":"Edwardsville","l":""},"164":{"n":"Effingham","l":""},"165":{"n":"El Dorado","l":""},"166":{"n":"Elbing","l":""},"167":{"n":"Elk City","l":""},"168":{"n":"Elk Falls","l":""},"169":{"n":"Elkhart","l":""},"170":{"n":"Ellinwood","l":""},"171":{"n":"Ellis","l":""},"172":{"n":"Ellsworth","l":""},"173":{"n":"Elmdale","l":""},"174":{"n":"Elsmore","l":""},"175":{"n":"Elwood","l":""},"176":{"n":"Emmett","l":""},"177":{"n":"Emporia","l":""},"178":{"n":"Englewood","l":""},"179":{"n":"Ensign","l":""},"180":{"n":"Enterprise","l":""},"181":{"n":"Erie","l":""},"182":{"n":"Esbon","l":""},"183":{"n":"Eskridge","l":""},"184":{"n":"Eudora","l":""},"185":{"n":"Eureka","l":""},"186":{"n":"Everest","l":""},"187":{"n":"Fairview","l":""},"188":{"n":"Fall River","l":""},"189":{"n":"Falun","l":""},"190":{"n":"Farlington","l":""},"191":{"n":"Florence","l":""},"192":{"n":"Fontana","l":""},"193":{"n":"Ford","l":""},"194":{"n":"Formoso","l":""},"195":{"n":"Fort Dodge","l":""},"196":{"n":"Fort Leavenworth","l":""},"197":{"n":"Fort Riley","l":""},"198":{"n":"Fort Scott","l":""},"199":{"n":"Fostoria","l":""},"200":{"n":"Fowler","l":""},"201":{"n":"Frankfort","l":""},"202":{"n":"Franklin","l":""},"203":{"n":"Fredonia","l":""},"204":{"n":"Freeport","l":""},"205":{"n":"Frontenac","l":""},"206":{"n":"Fulton","l":""},"207":{"n":"Galena","l":""},"208":{"n":"Galesburg","l":""},"209":{"n":"Galva","l":""},"210":{"n":"Garden City","l":""},"211":{"n":"Garden Plain","l":""},"212":{"n":"Gardner","l":""},"213":{"n":"Garfield","l":""},"214":{"n":"Garland","l":""},"215":{"n":"Garnett","l":""},"216":{"n":"Gas","l":""},"217":{"n":"Gaylord","l":""},"218":{"n":"Gem","l":""},"219":{"n":"Geneseo","l":""},"220":{"n":"Geuda Springs","l":""},"221":{"n":"Girard","l":""},"222":{"n":"Glade","l":""},"223":{"n":"Glasco","l":""},"224":{"n":"Glen Elder","l":""},"225":{"n":"Goddard","l":""},"226":{"n":"Goessel","l":""},"227":{"n":"Goff","l":""},"228":{"n":"Goodland","l":""},"229":{"n":"Gorham","l":""},"230":{"n":"Gove","l":""},"231":{"n":"Grainfield","l":""},"232":{"n":"Grantville","l":""},"233":{"n":"Great Bend","l":""},"234":{"n":"Greeley","l":""},"235":{"n":"Green","l":""},"236":{"n":"Greenleaf","l":""},"237":{"n":"Greensburg","l":""},"238":{"n":"Greenwich","l":""},"239":{"n":"Grenola","l":""},"240":{"n":"Gridley","l":""},"241":{"n":"Grinnell","l":""},"242":{"n":"Gypsum","l":""},"243":{"n":"Haddam","l":""},"244":{"n":"Halstead","l":""},"245":{"n":"Hamilton","l":""},"246":{"n":"Hanover","l":""},"247":{"n":"Hanston","l":""},"248":{"n":"Hardtner","l":""},"249":{"n":"Harper","l":""},"250":{"n":"Hartford","l":""},"251":{"n":"Harveyville","l":""},"252":{"n":"Havana","l":""},"253":{"n":"Haven","l":""},"254":{"n":"Havensville","l":""},"255":{"n":"Haviland","l":""},"256":{"n":"Hays","l":""},"257":{"n":"Haysville","l":""},"258":{"n":"Hazelton","l":""},"259":{"n":"Healy","l":""},"260":{"n":"Hepler","l":""},"261":{"n":"Herington","l":""},"262":{"n":"Herndon","l":""},"263":{"n":"Hesston","l":""},"264":{"n":"Hiawatha","l":""},"265":{"n":"Highland","l":""},"266":{"n":"Hill City","l":""},"267":{"n":"Hillsboro","l":""},"268":{"n":"Hillsdale","l":""},"269":{"n":"Hoisington","l":""},"270":{"n":"Holcomb","l":""},"271":{"n":"Hollenberg","l":""},"272":{"n":"Holton","l":""},"273":{"n":"Holyrood","l":""},"274":{"n":"Home","l":""},"275":{"n":"Hope","l":""},"276":{"n":"Horton","l":""},"277":{"n":"Howard","l":""},"278":{"n":"Hoxie","l":""},"279":{"n":"Hoyt","l":""},"280":{"n":"Hudson","l":""},"281":{"n":"Hugoton","l":""},"282":{"n":"Humboldt","l":""},"283":{"n":"Hunter","l":""},"284":{"n":"Hutchinson","l":""},"285":{"n":"Independence","l":""},"286":{"n":"Ingalls","l":""},"287":{"n":"Inman","l":""},"288":{"n":"Iola","l":""},"289":{"n":"Isabel","l":""},"290":{"n":"Iuka","l":""},"291":{"n":"Jamestown","l":""},"292":{"n":"Jennings","l":""},"293":{"n":"Jetmore","l":""},"294":{"n":"Jewell","l":""},"295":{"n":"Johnson","l":""},"296":{"n":"Junction City","l":""},"297":{"n":"Kanopolis","l":""},"298":{"n":"Kanorado","l":""},"299":{"n":"Kansas City","l":""},"300":{"n":"Kechi","l":""},"301":{"n":"Kendall","l":""},"302":{"n":"Kensington","l":""},"303":{"n":"Kincaid","l":""},"304":{"n":"Kingman","l":""},"305":{"n":"Kinsley","l":""},"306":{"n":"Kiowa","l":""},"307":{"n":"Kirwin","l":""},"308":{"n":"Kismet","l":""},"309":{"n":"La Crosse","l":""},"310":{"n":"La Harpe","l":""},"311":{"n":"Lacygne","l":""},"312":{"n":"Lake City","l":""},"313":{"n":"Lakin","l":""},"314":{"n":"Lamont","l":""},"315":{"n":"Lancaster","l":""},"316":{"n":"Lane","l":""},"317":{"n":"Lansing","l":""},"318":{"n":"Larned","l":""},"319":{"n":"Latham","l":""},"320":{"n":"Lawrence","l":""},"321":{"n":"Le Roy","l":""},"322":{"n":"Leavenworth","l":""},"323":{"n":"Leawood","l":""},"324":{"n":"Lebanon","l":""},"325":{"n":"Lebo","l":""},"326":{"n":"Lecompton","l":""},"327":{"n":"Lehigh","l":""},"328":{"n":"Lenexa","l":""},"329":{"n":"Lenora","l":""},"330":{"n":"Leon","l":""},"331":{"n":"Leonardville","l":""},"332":{"n":"Leoti","l":""},"333":{"n":"Levant","l":""},"334":{"n":"Lewis","l":""},"335":{"n":"Liberal","l":""},"336":{"n":"Liberty","l":""},"337":{"n":"Liebenthal","l":""},"338":{"n":"Lincoln","l":""},"339":{"n":"Lincolnville","l":""},"340":{"n":"Lindsborg","l":""},"341":{"n":"Linn","l":""},"342":{"n":"Linwood","l":""},"343":{"n":"Little River","l":""},"344":{"n":"Logan","l":""},"345":{"n":"Long Island","l":""},"346":{"n":"Longford","l":""},"347":{"n":"Longton","l":""},"348":{"n":"Lorraine","l":""},"349":{"n":"Lost Springs","l":""},"350":{"n":"Louisburg","l":""},"351":{"n":"Lucas","l":""},"352":{"n":"Ludell","l":""},"353":{"n":"Luray","l":""},"354":{"n":"Lyndon","l":""},"355":{"n":"Lyons","l":""},"356":{"n":"Macksville","l":""},"357":{"n":"Madison","l":""},"358":{"n":"Mahaska","l":""},"359":{"n":"Maize","l":""},"360":{"n":"Manhattan","l":""},"361":{"n":"Mankato","l":""},"362":{"n":"Manter","l":""},"363":{"n":"Maple City","l":""},"364":{"n":"Maple Hill","l":""},"365":{"n":"Mapleton","l":""},"366":{"n":"Marienthal","l":""},"367":{"n":"Marion","l":""},"368":{"n":"Marquette","l":""},"369":{"n":"Marysville","l":""},"370":{"n":"Matfield Green","l":""},"371":{"n":"Mayetta","l":""},"372":{"n":"Mayfield","l":""},"373":{"n":"Mc Cracken","l":""},"374":{"n":"Mc Cune","l":""},"375":{"n":"Mc Donald","l":""},"376":{"n":"Mc Farland","l":""},"377":{"n":"Mc Louth","l":""},"378":{"n":"Mcconnell Afb","l":""},"379":{"n":"Mcpherson","l":""},"380":{"n":"Meade","l":""},"381":{"n":"Medicine Lodge","l":""},"382":{"n":"Melvern","l":""},"383":{"n":"Meriden","l":""},"384":{"n":"Milan","l":""},"385":{"n":"Milford","l":""},"386":{"n":"Milton","l":""},"387":{"n":"Miltonvale","l":""},"388":{"n":"Minneapolis","l":""},"389":{"n":"Minneola","l":""},"390":{"n":"Mission","l":""},"391":{"n":"Moline","l":""},"392":{"n":"Montezuma","l":""},"393":{"n":"Monument","l":""},"394":{"n":"Moran","l":""},"395":{"n":"Morganville","l":""},"396":{"n":"Morland","l":""},"397":{"n":"Morrill","l":""},"398":{"n":"Morrowville","l":""},"399":{"n":"Moscow","l":""},"400":{"n":"Mound City","l":""},"401":{"n":"Mound Valley","l":""},"402":{"n":"Moundridge","l":""},"403":{"n":"Mount Hope","l":""},"404":{"n":"Mulberry","l":""},"405":{"n":"Mullinville","l":""},"406":{"n":"Mulvane","l":""},"407":{"n":"Munden","l":""},"408":{"n":"Murdock","l":""},"409":{"n":"Muscotah","l":""},"410":{"n":"Narka","l":""},"411":{"n":"Nashville","l":""},"412":{"n":"Natoma","l":""},"413":{"n":"Neal","l":""},"414":{"n":"Nekoma","l":""},"415":{"n":"Neodesha","l":""},"416":{"n":"Neosho Falls","l":""},"417":{"n":"Neosho Rapids","l":""},"418":{"n":"Ness City","l":""},"419":{"n":"Netawaka","l":""},"420":{"n":"New Albany","l":""},"421":{"n":"New Cambria","l":""},"422":{"n":"New Century","l":""},"423":{"n":"Newton","l":""},"424":{"n":"Nickerson","l":""},"425":{"n":"Niotaze","l":""},"426":{"n":"Norcatur","l":""},"427":{"n":"North Newton","l":""},"428":{"n":"Norton","l":""},"429":{"n":"Nortonville","l":""},"430":{"n":"Norway","l":""},"431":{"n":"Norwich","l":""},"432":{"n":"Oakley","l":""},"433":{"n":"Oberlin","l":""},"434":{"n":"Offerle","l":""},"435":{"n":"Ogallah","l":""},"436":{"n":"Ogden","l":""},"437":{"n":"Oketo","l":""},"438":{"n":"Olathe","l":""},"439":{"n":"Olmitz","l":""},"440":{"n":"Olpe","l":""},"441":{"n":"Olsburg","l":""},"442":{"n":"Onaga","l":""},"443":{"n":"Oneida","l":""},"444":{"n":"Opolis","l":""},"445":{"n":"Osage City","l":""},"446":{"n":"Osawatomie","l":""},"447":{"n":"Osborne","l":""},"448":{"n":"Oskaloosa","l":""},"449":{"n":"Oswego","l":""},"450":{"n":"Otis","l":""},"451":{"n":"Ottawa","l":""},"452":{"n":"Overbrook","l":""},"453":{"n":"Overland Park","l":""},"454":{"n":"Oxford","l":""},"455":{"n":"Ozawkie","l":""},"456":{"n":"Palco","l":""},"457":{"n":"Palmer","l":""},"458":{"n":"Paola","l":""},"459":{"n":"Paradise","l":""},"460":{"n":"Park","l":""},"461":{"n":"Parker","l":""},"462":{"n":"Parsons","l":""},"463":{"n":"Partridge","l":""},"464":{"n":"Pawnee Rock","l":""},"465":{"n":"Paxico","l":""},"466":{"n":"Peabody","l":""},"467":{"n":"Peck","l":""},"468":{"n":"Penokee","l":""},"469":{"n":"Perry","l":""},"470":{"n":"Peru","l":""},"471":{"n":"Pfeifer","l":""},"472":{"n":"Phillipsburg","l":""},"473":{"n":"Piedmont","l":""},"474":{"n":"Pierceville","l":""},"475":{"n":"Piqua","l":""},"476":{"n":"Pittsburg","l":""},"477":{"n":"Plains","l":""},"478":{"n":"Plainville","l":""},"479":{"n":"Pleasanton","l":""},"480":{"n":"Plevna","l":""},"481":{"n":"Pomona","l":""},"482":{"n":"Portis","l":""},"483":{"n":"Potter","l":""},"484":{"n":"Potwin","l":""},"485":{"n":"Powhattan","l":""},"486":{"n":"Prairie View","l":""},"487":{"n":"Prairie Village","l":""},"488":{"n":"Pratt","l":""},"489":{"n":"Prescott","l":""},"490":{"n":"Pretty Prairie","l":""},"491":{"n":"Princeton","l":""},"492":{"n":"Protection","l":""},"493":{"n":"Quenemo","l":""},"494":{"n":"Quinter","l":""},"495":{"n":"Ramona","l":""},"496":{"n":"Randall","l":""},"497":{"n":"Randolph","l":""},"498":{"n":"Ransom","l":""},"499":{"n":"Rantoul","l":""},"500":{"n":"Raymond","l":""},"501":{"n":"Reading","l":""},"502":{"n":"Redfield","l":""},"503":{"n":"Republic","l":""},"504":{"n":"Rexford","l":""},"505":{"n":"Richfield","l":""},"506":{"n":"Richmond","l":""},"507":{"n":"Riley","l":""},"508":{"n":"Riverton","l":""},"509":{"n":"Robinson","l":""},"510":{"n":"Rock","l":""},"511":{"n":"Rolla","l":""},"512":{"n":"Rosalia","l":""},"513":{"n":"Rose Hill","l":""},"514":{"n":"Rossville","l":""},"515":{"n":"Roxbury","l":""},"516":{"n":"Rozel","l":""},"517":{"n":"Rush Center","l":""},"518":{"n":"Russell","l":""},"519":{"n":"Sabetha","l":""},"520":{"n":"Saint Francis","l":""},"521":{"n":"Saint George","l":""},"522":{"n":"Saint John","l":""},"523":{"n":"Saint Marys","l":""},"524":{"n":"Saint Paul","l":""},"525":{"n":"Salina","l":""},"526":{"n":"Satanta","l":""},"527":{"n":"Savonburg","l":""},"528":{"n":"Sawyer","l":""},"529":{"n":"Scammon","l":""},"530":{"n":"Scandia","l":""},"531":{"n":"Schoenchen","l":""},"532":{"n":"Scott City","l":""},"533":{"n":"Scranton","l":""},"534":{"n":"Sedan","l":""},"535":{"n":"Sedgwick","l":""},"536":{"n":"Selden","l":""},"537":{"n":"Seneca","l":""},"538":{"n":"Severy","l":""},"539":{"n":"Sharon","l":""},"540":{"n":"Sharon Springs","l":""},"541":{"n":"Shawnee","l":""},"542":{"n":"Shawnee Mission","l":""},"543":{"n":"Silver Lake","l":""},"544":{"n":"Simpson","l":""},"545":{"n":"Smith Center","l":""},"546":{"n":"Soldier","l":""},"547":{"n":"Solomon","l":""},"548":{"n":"South Haven","l":""},"549":{"n":"South Hutchinson","l":""},"550":{"n":"Spearville","l":""},"551":{"n":"Spivey","l":""},"552":{"n":"Spring Hill","l":""},"553":{"n":"Stafford","l":""},"554":{"n":"Stark","l":""},"555":{"n":"Sterling","l":""},"556":{"n":"Stilwell","l":""},"557":{"n":"Stockton","l":""},"558":{"n":"Strong City","l":""},"559":{"n":"Sublette","l":""},"560":{"n":"Summerfield","l":""},"561":{"n":"Sun City","l":""},"562":{"n":"Sycamore","l":""},"563":{"n":"Sylvan Grove","l":""},"564":{"n":"Sylvia","l":""},"565":{"n":"Syracuse","l":""},"566":{"n":"Talmage","l":""},"567":{"n":"Tampa","l":""},"568":{"n":"Tecumseh","l":""},"569":{"n":"Tescott","l":""},"570":{"n":"Thayer","l":""},"571":{"n":"Tipton","l":""},"572":{"n":"Tonganoxie","l":""},"573":{"n":"Topeka","l":""},"574":{"n":"Toronto","l":""},"575":{"n":"Towanda","l":""},"576":{"n":"Treece","l":""},"577":{"n":"Tribune","l":""},"578":{"n":"Troy","l":""},"579":{"n":"Turon","l":""},"580":{"n":"Tyro","l":""},"581":{"n":"Udall","l":""},"582":{"n":"Ulysses","l":""},"583":{"n":"Uniontown","l":""},"584":{"n":"Utica","l":""},"585":{"n":"Valley Center","l":""},"586":{"n":"Valley Falls","l":""},"587":{"n":"Vassar","l":""},"588":{"n":"Vermillion","l":""},"589":{"n":"Victoria","l":""},"590":{"n":"Viola","l":""},"591":{"n":"Virgil","l":""},"592":{"n":"Wakarusa","l":""},"593":{"n":"Wakeeney","l":""},"594":{"n":"Wakefield","l":""},"595":{"n":"Waldo","l":""},"596":{"n":"Waldron","l":""},"597":{"n":"Walker","l":""},"598":{"n":"Wallace","l":""},"599":{"n":"Walnut","l":""},"600":{"n":"Walton","l":""},"601":{"n":"Wamego","l":""},"602":{"n":"Washington","l":""},"603":{"n":"Waterville","l":""},"604":{"n":"Wathena","l":""},"605":{"n":"Waverly","l":""},"606":{"n":"Webber","l":""},"607":{"n":"Weir","l":""},"608":{"n":"Welda","l":""},"609":{"n":"Wellington","l":""},"610":{"n":"Wellsville","l":""},"611":{"n":"Weskan","l":""},"612":{"n":"West Mineral","l":""},"613":{"n":"Westmoreland","l":""},"614":{"n":"Westphalia","l":""},"615":{"n":"Wetmore","l":""},"616":{"n":"White City","l":""},"617":{"n":"White Cloud","l":""},"618":{"n":"Whitewater","l":""},"619":{"n":"Whiting","l":""},"620":{"n":"Wichita","l":""},"621":{"n":"Williamsburg","l":""},"622":{"n":"Wilmore","l":""},"623":{"n":"Wilsey","l":""},"624":{"n":"Wilson","l":""},"625":{"n":"Winchester","l":""},"626":{"n":"Windom","l":""},"627":{"n":"Winfield","l":""},"628":{"n":"Winona","l":""},"629":{"n":"Woodbine","l":""},"630":{"n":"Woodston","l":""},"631":{"n":"Wright","l":""},"632":{"n":"Yates Center","l":""},"633":{"n":"Yoder","l":""},"634":{"n":"Zenda","l":""}}