{"1":{"n":"Abington","l":""},"2":{"n":"Accord","l":""},"3":{"n":"Acton","l":""},"4":{"n":"Acushnet","l":""},"5":{"n":"Adams","l":""},"6":{"n":"Agawam","l":""},"7":{"n":"Allston","l":""},"8":{"n":"Amesbury","l":""},"9":{"n":"Amherst","l":""},"10":{"n":"Andover","l":""},"11":{"n":"Arlington","l":""},"12":{"n":"Arlington Heights","l":""},"13":{"n":"Ashburnham","l":""},"14":{"n":"Ashby","l":""},"15":{"n":"Ashfield","l":""},"16":{"n":"Ashland","l":""},"17":{"n":"Ashley Falls","l":""},"18":{"n":"Assonet","l":""},"19":{"n":"Athol","l":""},"20":{"n":"Attleboro","l":""},"21":{"n":"Attleboro Falls","l":""},"22":{"n":"Auburn","l":""},"23":{"n":"Auburndale","l":""},"24":{"n":"Avon","l":""},"25":{"n":"Ayer","l":""},"26":{"n":"Babson Park","l":""},"27":{"n":"Baldwinville","l":""},"28":{"n":"Barnstable","l":""},"29":{"n":"Barre","l":""},"30":{"n":"Becket","l":""},"31":{"n":"Bedford","l":""},"32":{"n":"Belchertown","l":""},"33":{"n":"Bellingham","l":""},"34":{"n":"Belmont","l":""},"35":{"n":"Berkley","l":""},"36":{"n":"Berkshire","l":""},"37":{"n":"Berlin","l":""},"38":{"n":"Bernardston","l":""},"39":{"n":"Beverly","l":""},"40":{"n":"Billerica","l":""},"41":{"n":"Blackstone","l":""},"42":{"n":"Blandford","l":""},"43":{"n":"Bolton","l":""},"44":{"n":"Bondsville","l":""},"45":{"n":"Boston","l":""},"46":{"n":"Boxborough","l":""},"47":{"n":"Boxford","l":""},"48":{"n":"Boylston","l":""},"49":{"n":"Braintree","l":""},"50":{"n":"Brant Rock","l":""},"51":{"n":"Brewster","l":""},"52":{"n":"Bridgewater","l":""},"53":{"n":"Brighton","l":""},"54":{"n":"Brimfield","l":""},"55":{"n":"Brockton","l":""},"56":{"n":"Brookfield","l":""},"57":{"n":"Brookline","l":""},"58":{"n":"Brookline Village","l":""},"59":{"n":"Bryantville","l":""},"60":{"n":"Buckland","l":""},"61":{"n":"Burlington","l":""},"62":{"n":"Buzzards Bay","l":""},"63":{"n":"Byfield","l":""},"64":{"n":"Cambridge","l":""},"65":{"n":"Canton","l":""},"66":{"n":"Carlisle","l":""},"67":{"n":"Carver","l":""},"68":{"n":"Cataumet","l":""},"69":{"n":"Centerville","l":""},"70":{"n":"Charlemont","l":""},"71":{"n":"Charlestown","l":""},"72":{"n":"Charlton","l":""},"73":{"n":"Charlton City","l":""},"74":{"n":"Charlton Depot","l":""},"75":{"n":"Chartley","l":""},"76":{"n":"Chatham","l":""},"77":{"n":"Chelmsford","l":""},"78":{"n":"Chelsea","l":""},"79":{"n":"Cherry Valley","l":""},"80":{"n":"Cheshire","l":""},"81":{"n":"Chester","l":""},"82":{"n":"Chesterfield","l":""},"83":{"n":"Chestnut Hill","l":""},"84":{"n":"Chicopee","l":""},"85":{"n":"Chilmark","l":""},"86":{"n":"Clinton","l":""},"87":{"n":"Cohasset","l":""},"88":{"n":"Colrain","l":""},"89":{"n":"Concord","l":""},"90":{"n":"Conway","l":""},"91":{"n":"Cotuit","l":""},"92":{"n":"Cummaquid","l":""},"93":{"n":"Cummington","l":""},"94":{"n":"Cuttyhunk","l":""},"95":{"n":"Dalton","l":""},"96":{"n":"Danvers","l":""},"97":{"n":"Dartmouth","l":""},"98":{"n":"Dedham","l":""},"99":{"n":"Deerfield","l":""},"100":{"n":"Dennis","l":""},"101":{"n":"Dennis Port","l":""},"102":{"n":"Devens","l":""},"103":{"n":"Dighton","l":""},"104":{"n":"Douglas","l":""},"105":{"n":"Dover","l":""},"106":{"n":"Dracut","l":""},"107":{"n":"Drury","l":""},"108":{"n":"Dudley","l":""},"109":{"n":"Dunstable","l":""},"110":{"n":"Duxbury","l":""},"111":{"n":"East Boston","l":""},"112":{"n":"East Bridgewater","l":""},"113":{"n":"East Brookfield","l":""},"114":{"n":"East Dennis","l":""},"115":{"n":"East Falmouth","l":""},"116":{"n":"East Freetown","l":""},"117":{"n":"East Longmeadow","l":""},"118":{"n":"East Mansfield","l":""},"119":{"n":"East Orleans","l":""},"120":{"n":"East Otis","l":""},"121":{"n":"East Princeton","l":""},"122":{"n":"East Sandwich","l":""},"123":{"n":"East Taunton","l":""},"124":{"n":"East Templeton","l":""},"125":{"n":"East Walpole","l":""},"126":{"n":"East Wareham","l":""},"127":{"n":"East Weymouth","l":""},"128":{"n":"Eastham","l":""},"129":{"n":"Easthampton","l":""},"130":{"n":"Easton","l":""},"131":{"n":"Edgartown","l":""},"132":{"n":"Elmwood","l":""},"133":{"n":"Erving","l":""},"134":{"n":"Essex","l":""},"135":{"n":"Everett","l":""},"136":{"n":"Fairhaven","l":""},"137":{"n":"Fall River","l":""},"138":{"n":"Falmouth","l":""},"139":{"n":"Fayville","l":""},"140":{"n":"Feeding Hills","l":""},"141":{"n":"Fiskdale","l":""},"142":{"n":"Fitchburg","l":""},"143":{"n":"Forestdale","l":""},"144":{"n":"Foxboro","l":""},"145":{"n":"Framingham","l":""},"146":{"n":"Franklin","l":""},"147":{"n":"Gardner","l":""},"148":{"n":"Georgetown","l":""},"149":{"n":"Gilbertville","l":""},"150":{"n":"Gill","l":""},"151":{"n":"Glendale","l":""},"152":{"n":"Gloucester","l":""},"153":{"n":"Goshen","l":""},"154":{"n":"Grafton","l":""},"155":{"n":"Granby","l":""},"156":{"n":"Granville","l":""},"157":{"n":"Great Barrington","l":""},"158":{"n":"Green Harbor","l":""},"159":{"n":"Greenbush","l":""},"160":{"n":"Greenfield","l":""},"161":{"n":"Groton","l":""},"162":{"n":"Groveland","l":""},"163":{"n":"Hadley","l":""},"164":{"n":"Halifax","l":""},"165":{"n":"Hamilton","l":""},"166":{"n":"Hampden","l":""},"167":{"n":"Hanover","l":""},"168":{"n":"Hanscom Afb","l":""},"169":{"n":"Hanson","l":""},"170":{"n":"Hardwick","l":""},"171":{"n":"Harvard","l":""},"172":{"n":"Harwich","l":""},"173":{"n":"Harwich Port","l":""},"174":{"n":"Hatfield","l":""},"175":{"n":"Hathorne","l":""},"176":{"n":"Haverhill","l":""},"177":{"n":"Haydenville","l":""},"178":{"n":"Heath","l":""},"179":{"n":"Hingham","l":""},"180":{"n":"Hinsdale","l":""},"181":{"n":"Holbrook","l":""},"182":{"n":"Holden","l":""},"183":{"n":"Holland","l":""},"184":{"n":"Holliston","l":""},"185":{"n":"Holyoke","l":""},"186":{"n":"Hopedale","l":""},"187":{"n":"Hopkinton","l":""},"188":{"n":"Housatonic","l":""},"189":{"n":"Hubbardston","l":""},"190":{"n":"Hudson","l":""},"191":{"n":"Hull","l":""},"192":{"n":"Humarock","l":""},"193":{"n":"Huntington","l":""},"194":{"n":"Hyannis","l":""},"195":{"n":"Hyannis Port","l":""},"196":{"n":"Hyde Park","l":""},"197":{"n":"Ipswich","l":""},"198":{"n":"Jamaica Plain","l":""},"199":{"n":"Jefferson","l":""},"200":{"n":"Kingston","l":""},"201":{"n":"Lake Pleasant","l":""},"202":{"n":"Lakeville","l":""},"203":{"n":"Lancaster","l":""},"204":{"n":"Lanesboro","l":""},"205":{"n":"Lawrence","l":""},"206":{"n":"Lee","l":""},"207":{"n":"Leeds","l":""},"208":{"n":"Leicester","l":""},"209":{"n":"Lenox","l":""},"210":{"n":"Lenox Dale","l":""},"211":{"n":"Leominster","l":""},"212":{"n":"Leverett","l":""},"213":{"n":"Lexington","l":""},"214":{"n":"Lincoln","l":""},"215":{"n":"Linwood","l":""},"216":{"n":"Littleton","l":""},"217":{"n":"Longmeadow","l":""},"218":{"n":"Lowell","l":""},"219":{"n":"Ludlow","l":""},"220":{"n":"Lunenburg","l":""},"221":{"n":"Lynn","l":""},"222":{"n":"Lynnfield","l":""},"223":{"n":"Malden","l":""},"224":{"n":"Manchaug","l":""},"225":{"n":"Manchester","l":""},"226":{"n":"Manomet","l":""},"227":{"n":"Mansfield","l":""},"228":{"n":"Marblehead","l":""},"229":{"n":"Marion","l":""},"230":{"n":"Marlborough","l":""},"231":{"n":"Marshfield","l":""},"232":{"n":"Marshfield Hills","l":""},"233":{"n":"Marstons Mills","l":""},"234":{"n":"Mashpee","l":""},"235":{"n":"Mattapan","l":""},"236":{"n":"Mattapoisett","l":""},"237":{"n":"Maynard","l":""},"238":{"n":"Medfield","l":""},"239":{"n":"Medford","l":""},"240":{"n":"Medway","l":""},"241":{"n":"Melrose","l":""},"242":{"n":"Mendon","l":""},"243":{"n":"Menemsha","l":""},"244":{"n":"Merrimac","l":""},"245":{"n":"Methuen","l":""},"246":{"n":"Middleboro","l":""},"247":{"n":"Middlefield","l":""},"248":{"n":"Middleton","l":""},"249":{"n":"Milford","l":""},"250":{"n":"Mill River","l":""},"251":{"n":"Millbury","l":""},"252":{"n":"Millers Falls","l":""},"253":{"n":"Millis","l":""},"254":{"n":"Millville","l":""},"255":{"n":"Milton","l":""},"256":{"n":"Milton Village","l":""},"257":{"n":"Minot","l":""},"258":{"n":"Monponsett","l":""},"259":{"n":"Monroe Bridge","l":""},"260":{"n":"Monson","l":""},"261":{"n":"Montague","l":""},"262":{"n":"Monterey","l":""},"263":{"n":"Monument Beach","l":""},"264":{"n":"Nahant","l":""},"265":{"n":"Nantucket","l":""},"266":{"n":"Natick","l":""},"267":{"n":"Needham","l":""},"268":{"n":"Needham Heights","l":""},"269":{"n":"New Bedford","l":""},"270":{"n":"New Braintree","l":""},"271":{"n":"New Salem","l":""},"272":{"n":"New Town","l":""},"273":{"n":"Newbury","l":""},"274":{"n":"Newburyport","l":""},"275":{"n":"Newton","l":""},"276":{"n":"Newton Center","l":""},"277":{"n":"Newton Highlands","l":""},"278":{"n":"Newton Lower Falls","l":""},"279":{"n":"Newton Upper Falls","l":""},"280":{"n":"Newtonville","l":""},"281":{"n":"Nonantum","l":""},"282":{"n":"Norfolk","l":""},"283":{"n":"North Adams","l":""},"284":{"n":"North Amherst","l":""},"285":{"n":"North Andover","l":""},"286":{"n":"North Attleboro","l":""},"287":{"n":"North Billerica","l":""},"288":{"n":"North Brookfield","l":""},"289":{"n":"North Carver","l":""},"290":{"n":"North Chatham","l":""},"291":{"n":"North Chelmsford","l":""},"292":{"n":"North Dartmouth","l":""},"293":{"n":"North Dighton","l":""},"294":{"n":"North Eastham","l":""},"295":{"n":"North Easton","l":""},"296":{"n":"North Egremont","l":""},"297":{"n":"North Falmouth","l":""},"298":{"n":"North Grafton","l":""},"299":{"n":"North Hatfield","l":""},"300":{"n":"North Marshfield","l":""},"301":{"n":"North Oxford","l":""},"302":{"n":"North Pembroke","l":""},"303":{"n":"North Reading","l":""},"304":{"n":"North Scituate","l":""},"305":{"n":"North Truro","l":""},"306":{"n":"North Uxbridge","l":""},"307":{"n":"North Waltham","l":""},"308":{"n":"North Weymouth","l":""},"309":{"n":"Northampton","l":""},"310":{"n":"Northborough","l":""},"311":{"n":"Northbridge","l":""},"312":{"n":"Northfield","l":""},"313":{"n":"Norton","l":""},"314":{"n":"Norwell","l":""},"315":{"n":"Norwood","l":""},"316":{"n":"Nutting Lake","l":""},"317":{"n":"Oak Bluffs","l":""},"318":{"n":"Oakham","l":""},"319":{"n":"Ocean Bluff","l":""},"320":{"n":"Onset","l":""},"321":{"n":"Orange","l":""},"322":{"n":"Orleans","l":""},"323":{"n":"Osterville","l":""},"324":{"n":"Otis","l":""},"325":{"n":"Oxford","l":""},"326":{"n":"Palmer","l":""},"327":{"n":"Paxton","l":""},"328":{"n":"Peabody","l":""},"329":{"n":"Pembroke","l":""},"330":{"n":"Pepperell","l":""},"331":{"n":"Petersham","l":""},"332":{"n":"Pinehurst","l":""},"333":{"n":"Pittsfield","l":""},"334":{"n":"Plainfield","l":""},"335":{"n":"Plainville","l":""},"336":{"n":"Plymouth","l":""},"337":{"n":"Plympton","l":""},"338":{"n":"Pocasset","l":""},"339":{"n":"Prides Crossing","l":""},"340":{"n":"Princeton","l":""},"341":{"n":"Provincetown","l":""},"342":{"n":"Quincy","l":""},"343":{"n":"Randolph","l":""},"344":{"n":"Raynham","l":""},"345":{"n":"Raynham Center","l":""},"346":{"n":"Reading","l":""},"347":{"n":"Readville","l":""},"348":{"n":"Rehoboth","l":""},"349":{"n":"Revere","l":""},"350":{"n":"Richmond","l":""},"351":{"n":"Rochdale","l":""},"352":{"n":"Rochester","l":""},"353":{"n":"Rockland","l":""},"354":{"n":"Rockport","l":""},"355":{"n":"Roslindale","l":""},"356":{"n":"Rowe","l":""},"357":{"n":"Rowley","l":""},"358":{"n":"Royalston","l":""},"359":{"n":"Russell","l":""},"360":{"n":"Rutland","l":""},"361":{"n":"Sagamore","l":""},"362":{"n":"Sagamore Beach","l":""},"363":{"n":"Salem","l":""},"364":{"n":"Salisbury","l":""},"365":{"n":"Sandisfield","l":""},"366":{"n":"Sandwich","l":""},"367":{"n":"Saugus","l":""},"368":{"n":"Savoy","l":""},"369":{"n":"Scituate","l":""},"370":{"n":"Seekonk","l":""},"371":{"n":"Sharon","l":""},"372":{"n":"Sheffield","l":""},"373":{"n":"Shelburne Falls","l":""},"374":{"n":"Sheldonville","l":""},"375":{"n":"Sherborn","l":""},"376":{"n":"Shirley","l":""},"377":{"n":"Shrewsbury","l":""},"378":{"n":"Shutesbury","l":""},"379":{"n":"Siasconset","l":""},"380":{"n":"Silver Beach","l":""},"381":{"n":"Somerset","l":""},"382":{"n":"Somerville","l":""},"383":{"n":"South Barre","l":""},"384":{"n":"South Carver","l":""},"385":{"n":"South Chatham","l":""},"386":{"n":"South Dartmouth","l":""},"387":{"n":"South Deerfield","l":""},"388":{"n":"South Dennis","l":""},"389":{"n":"South Easton","l":""},"390":{"n":"South Egremont","l":""},"391":{"n":"South Grafton","l":""},"392":{"n":"South Hadley","l":""},"393":{"n":"South Hamilton","l":""},"394":{"n":"South Harwich","l":""},"395":{"n":"South Lancaster","l":""},"396":{"n":"South Lee","l":""},"397":{"n":"South Orleans","l":""},"398":{"n":"South Walpole","l":""},"399":{"n":"South Wellfleet","l":""},"400":{"n":"South Weymouth","l":""},"401":{"n":"South Yarmouth","l":""},"402":{"n":"Southampton","l":""},"403":{"n":"Southborough","l":""},"404":{"n":"Southbridge","l":""},"405":{"n":"Southfield","l":""},"406":{"n":"Southwick","l":""},"407":{"n":"Spencer","l":""},"408":{"n":"Springfield","l":""},"409":{"n":"Sterling","l":""},"410":{"n":"Still River","l":""},"411":{"n":"Stockbridge","l":""},"412":{"n":"Stoneham","l":""},"413":{"n":"Stoughton","l":""},"414":{"n":"Stow","l":""},"415":{"n":"Sturbridge","l":""},"416":{"n":"Sudbury","l":""},"417":{"n":"Sunderland","l":""},"418":{"n":"Sutton","l":""},"419":{"n":"Swampscott","l":""},"420":{"n":"Swansea","l":""},"421":{"n":"Taunton","l":""},"422":{"n":"Templeton","l":""},"423":{"n":"Tewksbury","l":""},"424":{"n":"Thorndike","l":""},"425":{"n":"Three Rivers","l":""},"426":{"n":"Topsfield","l":""},"427":{"n":"Townsend","l":""},"428":{"n":"Truro","l":""},"429":{"n":"Turners Falls","l":""},"430":{"n":"Tyngsboro","l":""},"431":{"n":"Tyringham","l":""},"432":{"n":"Upton","l":""},"433":{"n":"Uxbridge","l":""},"434":{"n":"Village Of Nagog Woods","l":""},"435":{"n":"Vineyard Haven","l":""},"436":{"n":"Waban","l":""},"437":{"n":"Wakefield","l":""},"438":{"n":"Wales","l":""},"439":{"n":"Walpole","l":""},"440":{"n":"Waltham","l":""},"441":{"n":"Ware","l":""},"442":{"n":"Wareham","l":""},"443":{"n":"Warren","l":""},"444":{"n":"Warwick","l":""},"445":{"n":"Watertown","l":""},"446":{"n":"Waverley","l":""},"447":{"n":"Wayland","l":""},"448":{"n":"Webster","l":""},"449":{"n":"Wellesley","l":""},"450":{"n":"Wellesley Hills","l":""},"451":{"n":"Wellfleet","l":""},"452":{"n":"Wendell","l":""},"453":{"n":"Wendell Depot","l":""},"454":{"n":"Wenham","l":""},"455":{"n":"West Barnstable","l":""},"456":{"n":"West Boxford","l":""},"457":{"n":"West Boylston","l":""},"458":{"n":"West Bridgewater","l":""},"459":{"n":"West Brookfield","l":""},"460":{"n":"West Chatham","l":""},"461":{"n":"West Chesterfield","l":""},"462":{"n":"West Chop","l":""},"463":{"n":"West Dennis","l":""},"464":{"n":"West Falmouth","l":""},"465":{"n":"West Groton","l":""},"466":{"n":"West Harwich","l":""},"467":{"n":"West Hatfield","l":""},"468":{"n":"West Hyannisport","l":""},"469":{"n":"West Medford","l":""},"470":{"n":"West Millbury","l":""},"471":{"n":"West Newbury","l":""},"472":{"n":"West Newton","l":""},"473":{"n":"West Roxbury","l":""},"474":{"n":"West Springfield","l":""},"475":{"n":"West Stockbridge","l":""},"476":{"n":"West Tisbury","l":""},"477":{"n":"West Townsend","l":""},"478":{"n":"West Wareham","l":""},"479":{"n":"West Warren","l":""},"480":{"n":"West Yarmouth","l":""},"481":{"n":"Westborough","l":""},"482":{"n":"Westfield","l":""},"483":{"n":"Westford","l":""},"484":{"n":"Westminster","l":""},"485":{"n":"Weston","l":""},"486":{"n":"Westport","l":""},"487":{"n":"Westport Point","l":""},"488":{"n":"Westwood","l":""},"489":{"n":"Weymouth","l":""},"490":{"n":"Whately","l":""},"491":{"n":"Wheelwright","l":""},"492":{"n":"White Horse Beach","l":""},"493":{"n":"Whitinsville","l":""},"494":{"n":"Whitman","l":""},"495":{"n":"Wilbraham","l":""},"496":{"n":"Williamsburg","l":""},"497":{"n":"Williamstown","l":""},"498":{"n":"Wilmington","l":""},"499":{"n":"Winchendon","l":""},"500":{"n":"Winchendon Springs","l":""},"501":{"n":"Winchester","l":""},"502":{"n":"Windsor","l":""},"503":{"n":"Winthrop","l":""},"504":{"n":"Woburn","l":""},"505":{"n":"Woods Hole","l":""},"506":{"n":"Woodville","l":""},"507":{"n":"Worcester","l":""},"508":{"n":"Woronoco","l":""},"509":{"n":"Worthington","l":""},"510":{"n":"Wrentham","l":""},"511":{"n":"Yarmouth Port","l":""}}