{
  "1": {
    "n": "Baltimore",
    "l": "Baltimore"
  },
  "2": {
    "n": "Frederick",
    "l": "Frederick"
  },
  "3": {
    "n": "Rockville",
    "l": "Rockville"
  },
  "4": {
    "n": "Gaithersburg",
    "l": "Gaithersburg"
  },
  "5": {
    "n": "Bowie",
    "l": "Bowie"
  },
  "6": {
    "n": "Hagerstown",
    "l": "Hagerstown"
  },
  "7": {
    "n": "Annapolis",
    "l": "Annapolis"
  },
  "8": {
    "n": "College Park",
    "l": "College Park"
  },
  "9": {
    "n": "Salisbury",
    "l": "Salisbury"
  },
  "10": {
    "n": "Laurel",
    "l": "Laurel"
  }
}
