{
  "1": {
    "n": "New York City",
    "l": "New York City"
  },
  "2": {
    "n": "Buffalo",
    "l": "Buffalo"
  },
  "3": {
    "n": "Rochester",
    "l": "Rochester"
  },
  "4": {
    "n": "Yonkers",
    "l": "Yonkers"
  },
  "5": {
    "n": "Syracuse",
    "l": "Syracuse"
  },
  "6": {
    "n": "Albany",
    "l": "Albany"
  },
  "7": {
    "n": "New Rochelle",
    "l": "New Rochelle"
  },
  "8": {
    "n": "Mount Vernon",
    "l": "Mount Vernon"
  },
  "9": {
    "n": "Schenectady",
    "l": "Schenectady"
  },
  "10": {
    "n": "Utica",
    "l": "Utica"
  }
}
