{"1":{"n":"Adamant","l":""},"2":{"n":"Albany","l":""},"3":{"n":"Alburgh","l":""},"4":{"n":"Arlington","l":""},"5":{"n":"Ascutney","l":""},"6":{"n":"Averill","l":""},"7":{"n":"Bakersfield","l":""},"8":{"n":"Barnard","l":""},"9":{"n":"Barnet","l":""},"10":{"n":"Barre","l":""},"11":{"n":"Barton","l":""},"12":{"n":"Beebe Plain","l":""},"13":{"n":"Beecher Falls","l":""},"14":{"n":"Bellows Falls","l":""},"15":{"n":"Belmont","l":""},"16":{"n":"Belvidere Center","l":""},"17":{"n":"Bennington","l":""},"18":{"n":"Benson","l":""},"19":{"n":"Bethel","l":""},"20":{"n":"Bomoseen","l":""},"21":{"n":"Bondville","l":""},"22":{"n":"Bradford","l":""},"23":{"n":"Brandon","l":""},"24":{"n":"Brattleboro","l":""},"25":{"n":"Bridgewater","l":""},"26":{"n":"Bridgewater Corners","l":""},"27":{"n":"Bridport","l":""},"28":{"n":"Bristol","l":""},"29":{"n":"Brookfield","l":""},"30":{"n":"Brownsville","l":""},"31":{"n":"Burlington","l":""},"32":{"n":"Cabot","l":""},"33":{"n":"Calais","l":""},"34":{"n":"Cambridge","l":""},"35":{"n":"Cambridgeport","l":""},"36":{"n":"Canaan","l":""},"37":{"n":"Castleton","l":""},"38":{"n":"Cavendish","l":""},"39":{"n":"Center Rutland","l":""},"40":{"n":"Charlotte","l":""},"41":{"n":"Chelsea","l":""},"42":{"n":"Chester","l":""},"43":{"n":"Chester Depot","l":""},"44":{"n":"Chittenden","l":""},"45":{"n":"Colchester","l":""},"46":{"n":"Concord","l":""},"47":{"n":"Corinth","l":""},"48":{"n":"Coventry","l":""},"49":{"n":"Craftsbury","l":""},"50":{"n":"Craftsbury Common","l":""},"51":{"n":"Cuttingsville","l":""},"52":{"n":"Danby","l":""},"53":{"n":"Danville","l":""},"54":{"n":"Derby","l":""},"55":{"n":"Derby Line","l":""},"56":{"n":"Dorset","l":""},"57":{"n":"East Arlington","l":""},"58":{"n":"East Barre","l":""},"59":{"n":"East Berkshire","l":""},"60":{"n":"East Burke","l":""},"61":{"n":"East Calais","l":""},"62":{"n":"East Charleston","l":""},"63":{"n":"East Corinth","l":""},"64":{"n":"East Dorset","l":""},"65":{"n":"East Dover","l":""},"66":{"n":"East Fairfield","l":""},"67":{"n":"East Hardwick","l":""},"68":{"n":"East Haven","l":""},"69":{"n":"East Middlebury","l":""},"70":{"n":"East Montpelier","l":""},"71":{"n":"East Poultney","l":""},"72":{"n":"East Randolph","l":""},"73":{"n":"East Ryegate","l":""},"74":{"n":"East Saint Johnsbury","l":""},"75":{"n":"East Thetford","l":""},"76":{"n":"East Wallingford","l":""},"77":{"n":"Eden","l":""},"78":{"n":"Eden Mills","l":""},"79":{"n":"Enosburg Falls","l":""},"80":{"n":"Essex","l":""},"81":{"n":"Essex Junction","l":""},"82":{"n":"Fair Haven","l":""},"83":{"n":"Fairfax","l":""},"84":{"n":"Fairfield","l":""},"85":{"n":"Fairlee","l":""},"86":{"n":"Ferrisburgh","l":""},"87":{"n":"Florence","l":""},"88":{"n":"Forest Dale","l":""},"89":{"n":"Franklin","l":""},"90":{"n":"Gaysville","l":""},"91":{"n":"Gilman","l":""},"92":{"n":"Glover","l":""},"93":{"n":"Grafton","l":""},"94":{"n":"Granby","l":""},"95":{"n":"Grand Isle","l":""},"96":{"n":"Graniteville","l":""},"97":{"n":"Granville","l":""},"98":{"n":"Greensboro","l":""},"99":{"n":"Greensboro Bend","l":""},"100":{"n":"Groton","l":""},"101":{"n":"Guildhall","l":""},"102":{"n":"Hancock","l":""},"103":{"n":"Hardwick","l":""},"104":{"n":"Hartford","l":""},"105":{"n":"Hartland","l":""},"106":{"n":"Hartland Four Corners","l":""},"107":{"n":"Highgate Center","l":""},"108":{"n":"Highgate Springs","l":""},"109":{"n":"Hinesburg","l":""},"110":{"n":"Huntington","l":""},"111":{"n":"Hyde Park","l":""},"112":{"n":"Hydeville","l":""},"113":{"n":"Irasburg","l":""},"114":{"n":"Island Pond","l":""},"115":{"n":"Isle La Motte","l":""},"116":{"n":"Jacksonville","l":""},"117":{"n":"Jamaica","l":""},"118":{"n":"Jeffersonville","l":""},"119":{"n":"Jericho","l":""},"120":{"n":"Johnson","l":""},"121":{"n":"Jonesville","l":""},"122":{"n":"Killington","l":""},"123":{"n":"Lake Elmore","l":""},"124":{"n":"Londonderry","l":""},"125":{"n":"Lowell","l":""},"126":{"n":"Lower Waterford","l":""},"127":{"n":"Ludlow","l":""},"128":{"n":"Lunenburg","l":""},"129":{"n":"Lyndon","l":""},"130":{"n":"Lyndon Center","l":""},"131":{"n":"Lyndonville","l":""},"132":{"n":"Manchester","l":""},"133":{"n":"Manchester Center","l":""},"134":{"n":"Marlboro","l":""},"135":{"n":"Marshfield","l":""},"136":{"n":"Mc Indoe Falls","l":""},"137":{"n":"Middlebury","l":""},"138":{"n":"Middletown Springs","l":""},"139":{"n":"Milton","l":""},"140":{"n":"Monkton","l":""},"141":{"n":"Montgomery","l":""},"142":{"n":"Montgomery Center","l":""},"143":{"n":"Montpelier","l":""},"144":{"n":"Moretown","l":""},"145":{"n":"Morgan","l":""},"146":{"n":"Morrisville","l":""},"147":{"n":"Moscow","l":""},"148":{"n":"Mount Holly","l":""},"149":{"n":"New Haven","l":""},"150":{"n":"Newbury","l":""},"151":{"n":"Newfane","l":""},"152":{"n":"Newport","l":""},"153":{"n":"Newport Center","l":""},"154":{"n":"North Bennington","l":""},"155":{"n":"North Clarendon","l":""},"156":{"n":"North Concord","l":""},"157":{"n":"North Ferrisburgh","l":""},"158":{"n":"North Hartland","l":""},"159":{"n":"North Hero","l":""},"160":{"n":"North Hyde Park","l":""},"161":{"n":"North Montpelier","l":""},"162":{"n":"North Pomfret","l":""},"163":{"n":"North Pownal","l":""},"164":{"n":"North Springfield","l":""},"165":{"n":"North Thetford","l":""},"166":{"n":"North Troy","l":""},"167":{"n":"Northfield","l":""},"168":{"n":"Northfield Falls","l":""},"169":{"n":"Norton","l":""},"170":{"n":"Norwich","l":""},"171":{"n":"Orleans","l":""},"172":{"n":"Orwell","l":""},"173":{"n":"Passumpsic","l":""},"174":{"n":"Pawlet","l":""},"175":{"n":"Peacham","l":""},"176":{"n":"Perkinsville","l":""},"177":{"n":"Peru","l":""},"178":{"n":"Pittsfield","l":""},"179":{"n":"Pittsford","l":""},"180":{"n":"Plainfield","l":""},"181":{"n":"Plymouth","l":""},"182":{"n":"Post Mills","l":""},"183":{"n":"Poultney","l":""},"184":{"n":"Pownal","l":""},"185":{"n":"Proctor","l":""},"186":{"n":"Proctorsville","l":""},"187":{"n":"Putney","l":""},"188":{"n":"Quechee","l":""},"189":{"n":"Randolph","l":""},"190":{"n":"Randolph Center","l":""},"191":{"n":"Reading","l":""},"192":{"n":"Readsboro","l":""},"193":{"n":"Richford","l":""},"194":{"n":"Richmond","l":""},"195":{"n":"Ripton","l":""},"196":{"n":"Rochester","l":""},"197":{"n":"Roxbury","l":""},"198":{"n":"Rupert","l":""},"199":{"n":"Rutland","l":""},"200":{"n":"Saint Albans","l":""},"201":{"n":"Saint Albans Bay","l":""},"202":{"n":"Saint Johnsbury","l":""},"203":{"n":"Saint Johnsbury Center","l":""},"204":{"n":"Salisbury","l":""},"205":{"n":"Saxtons River","l":""},"206":{"n":"Shaftsbury","l":""},"207":{"n":"Sharon","l":""},"208":{"n":"Sheffield","l":""},"209":{"n":"Shelburne","l":""},"210":{"n":"Sheldon","l":""},"211":{"n":"Sheldon Springs","l":""},"212":{"n":"Shoreham","l":""},"213":{"n":"South Barre","l":""},"214":{"n":"South Burlington","l":""},"215":{"n":"South Hero","l":""},"216":{"n":"South Londonderry","l":""},"217":{"n":"South Newfane","l":""},"218":{"n":"South Pomfret","l":""},"219":{"n":"South Royalton","l":""},"220":{"n":"South Ryegate","l":""},"221":{"n":"South Strafford","l":""},"222":{"n":"South Woodstock","l":""},"223":{"n":"Springfield","l":""},"224":{"n":"Stamford","l":""},"225":{"n":"Starksboro","l":""},"226":{"n":"Stockbridge","l":""},"227":{"n":"Stowe","l":""},"228":{"n":"Strafford","l":""},"229":{"n":"Sutton","l":""},"230":{"n":"Swanton","l":""},"231":{"n":"Taftsville","l":""},"232":{"n":"Thetford","l":""},"233":{"n":"Thetford Center","l":""},"234":{"n":"Topsham","l":""},"235":{"n":"Townshend","l":""},"236":{"n":"Troy","l":""},"237":{"n":"Tunbridge","l":""},"238":{"n":"Underhill","l":""},"239":{"n":"Underhill Center","l":""},"240":{"n":"Vergennes","l":""},"241":{"n":"Vernon","l":""},"242":{"n":"Vershire","l":""},"243":{"n":"Waitsfield","l":""},"244":{"n":"Wallingford","l":""},"245":{"n":"Wardsboro","l":""},"246":{"n":"Warren","l":""},"247":{"n":"Washington","l":""},"248":{"n":"Waterbury","l":""},"249":{"n":"Waterbury Center","l":""},"250":{"n":"Waterville","l":""},"251":{"n":"Websterville","l":""},"252":{"n":"Wells","l":""},"253":{"n":"Wells River","l":""},"254":{"n":"West Burke","l":""},"255":{"n":"West Charleston","l":""},"256":{"n":"West Danville","l":""},"257":{"n":"West Dover","l":""},"258":{"n":"West Dummerston","l":""},"259":{"n":"West Fairlee","l":""},"260":{"n":"West Glover","l":""},"261":{"n":"West Halifax","l":""},"262":{"n":"West Hartford","l":""},"263":{"n":"West Newbury","l":""},"264":{"n":"West Pawlet","l":""},"265":{"n":"West Rupert","l":""},"266":{"n":"West Rutland","l":""},"267":{"n":"West Topsham","l":""},"268":{"n":"West Townshend","l":""},"269":{"n":"West Wardsboro","l":""},"270":{"n":"Westfield","l":""},"271":{"n":"Westford","l":""},"272":{"n":"Westminster","l":""},"273":{"n":"Westminster Station","l":""},"274":{"n":"Weston","l":""},"275":{"n":"White River Junction","l":""},"276":{"n":"Whiting","l":""},"277":{"n":"Whitingham","l":""},"278":{"n":"Wilder","l":""},"279":{"n":"Williamstown","l":""},"280":{"n":"Williamsville","l":""},"281":{"n":"Williston","l":""},"282":{"n":"Wilmington","l":""},"283":{"n":"Windsor","l":""},"284":{"n":"Winooski","l":""},"285":{"n":"Wolcott","l":""},"286":{"n":"Woodbury","l":""},"287":{"n":"Woodstock","l":""},"288":{"n":"Worcester","l":""}}