{
  "1": {"n": "Salzburg", "l": "Salzburg"},
  "2": {"n": "Hallein", "l": "Hallein"},
  "3": {"n": "Bischofshofen", "l": "Bischofshofen"},
  "4": {"n": "Mittersill", "l": "Mittersill"},
  "5": {"n": "Radstadt", "l": "Radstadt"},
  "6": {"n": "Saalfelden am Steinernen Meer", "l": "Saalfelden am Steinernen Meer"},
  "7": {"n": "Sankt Johann im Pongau", "l": "Sankt Johann im Pongau"},
  "8": {"n": "Seekirchen am Wallersee", "l": "Seekirchen am Wallersee"},
  "9": {"n": "Tamsweg", "l": "Tamsweg"},
  "10": {"n": "Zell am See", "l": "Zell am See"}
}
